Workbook
Name Slicer_Bank_Name: #N/A
Name Slicer_Gender: #N/A
Name Slicer_State: #N/A

Sheet data
A1: Transaction_ID | B1: Transaction_Date | C1: Day | D1: Transaction_Time | E1: hour | F1: UPI_App | G1: Customer_ID | H1: Age_Group | I1: Gender | J1: State | K1: City | L1: Merchant_Name | M1: Merchant_Category | N1: Transaction_Type | O1: Payment_Mode | P1: Bank_Name | Q1: Amount_INR | R1: Cashback_INR | S1: Transaction_Fee_INR | T1: Status | U1: Failure_Reason | V1: Device_OS | W1: Risk_Score | X1: Is_Suspected_Fraud
A2: UPI202605P2_0000001 | B2: 46170 | C2: =TEXT(Table3[[#This Row],[Transaction_Date]],"dddd") -> Thursday | D2: 17:01:47 | E2: =HOUR(Table3[[#This Row],[Transaction_Time]]) -> 17 | F2: PhonePe | G2: CUST882856 | H2: 25-34 | I2: Male | J2: Telangana | K2: Warangal | L2: Topmate | M2: Education | N2: P2P | O2: Bank Account | P2: Bank of Baroda | Q2: 572.53 | R2: 51.8 | S2: 0 | T2: Success | V2: iOS | W2: 7 | X2: No
A3: UPI202605P2_0000002 | B3: 46152 | C3: =TEXT(Table3[[#This Row],[Transaction_Date]],"dddd") -> Sunday | D3: 12:14:08 | E3: =HOUR(Table3[[#This Row],[Transaction_Time]]) -> 12 | F3: Google Pay | G3: CUST170502 | H3: 25-34 | I3: Female | J3: Tamil Nadu | K3: Chennai | L3: Udemy | M3: Education | N3: P2M | O3: UPI ID | P3: Axis Bank | Q3: 415.75 | R3: 0 | S3: 0 | T3: Success | V3: Android | W3: 72 | X3: No
A4: UPI202605P2_0000003 | B4: 46146 | C4: =TEXT(Table3[[#This Row],[Transaction_Date]],"dddd") -> Monday | D4: 19:43:47 | E4: =HOUR(Table3[[#This Row],[Transaction_Time]]) -> 19 | F4: Paytm | G4: CUST107673 | H4: 35-44 | I4: Male | J4: Delhi | K4: New Delhi | L4: Local Clinic | M4: Healthcare | N4: Bill Payment | O4: QR Scan | P4: Punjab National Bank | Q4: 1007.05 | R4: 22.81 | S4: 0 | T4: Success | V4: Android | W4: 29 | X4: No
A5: UPI202605P2_0000004 | B5: 46156 | C5: =TEXT(Table3[[#This Row],[Transaction_Date]],"dddd") -> Thursday | D5: 20:05:37 | E5: =HOUR(Table3[[#This Row],[Transaction_Time]]) -> 20 | F5: PhonePe | G5: CUST817281 | H5: 35-44 | I5: Female | J5: Telangana | K5: Nizamabad | L5: Indian Oil | M5: Fuel | N5: P2M | O5: QR Scan | P5: HDFC Bank | Q5: 390.86 | R5: 0 | S5: 0 | T5: Success | V5: Android | W5: 93 | X5: Yes
A6: UPI202605P2_0000005 | B6: 46153 | C6: =TEXT(Table3[[#This Row],[Transaction_Date]],"dddd") -> Monday | D6: 14:01:05 | E6: =HOUR(Table3[[#This Row],[Transaction_Time]]) -> 14 | F6: Amazon Pay | G6: CUST513285 | H6: 45-54 | I6: Female | J6: Gujarat | K6: Surat | L6: Data Tutorials | M6: Education | N6: Online Shopping | O6: UPI ID | P6: Punjab National Bank | Q6: 165.15 | R6: 15.37 | S6: 0 | T6: Success | V6: iOS | W6: 25 | X6: No
A7: UPI202605P2_0000006 | B7: 46143 | C7: =TEXT(Table3[[#This Row],[Transaction_Date]],"dddd") -> Friday | D7: 11:32:38 | E7: =HOUR(Table3[[#This Row],[Transaction_Time]]) -> 11 | F7: Google Pay | G7: CUST980289 | H7: 45-54 | I7: Female | J7: Gujarat | K7: Surat | L7: Jio | M7: Recharge & Bills | N7: P2M | O7: UPI ID | P7: SBI | Q7: 135.39 | R7: 0 | S7: 2.79 | T7: Success | V7: Android | W7: 75 | X7: No
A8: UPI202605P2_0000007 | B8: 46157 | C8: =TEXT(Table3[[#This Row],[Transaction_Date]],"dddd") -> Friday | D8: 07:12:45 | E8: =HOUR(Table3[[#This Row],[Transaction_Time]]) -> 7 | F8: Cred Pay | G8: CUST245668 | H8: 18-24 | I8: Male | J8: Madhya Pradesh | K8: Jabalpur | L8: Zomato | M8: Food & Dining | N8: P2M | O8: QR Scan | P8: HDFC Bank | Q8: 169.57 | R8: 15.45 | S8: 0 | T8: Success | V8: Android | W8: 81 | X8: No
A9: UPI202605P2_0000008 | B9: 46160 | C9: =TEXT(Table3[[#This Row],[Transaction_Date]],"dddd") -> Monday | D9: 18:34:26 | E9: =HOUR(Table3[[#This Row],[Transaction_Time]]) -> 18 | F9: PhonePe | G9: CUST780035 | H9: 55+ | I9: Male | J9: Rajasthan | K9: Udaipur | L9: Myntra | M9: Shopping | N9: P2M | O9: UPI ID | P9: HDFC Bank | Q9: 936.58 | R9: 0 | S9: 3.76 | T9: Success | V9: Android | W9: 23 | X9: No
A10: UPI202605P2_0000009 | B10: 46144 | C10: =TEXT(Table3[[#This Row],[Transaction_Date]],"dddd") -> Saturday | D10: 11:37:17 | E10: =HOUR(Table3[[#This Row],[Transaction_Time]]) -> 11 | F10: PhonePe | G10: CUST954499 | H10: 25-34 | I10: Female | J10: West Bengal | K10: Kolkata | L10: McDonalds | M10: Food & Dining | N10: P2M | O10: UPI ID | P10: Kotak Mahindra Bank | Q10: 316.48 | R10: 0 | S10: 7.64 | T10: Success | V10: Android | W10: 88 | X10: No
A11: UPI202605P2_0000010 | B11: 46171 | C11: =TEXT(Table3[[#This Row],[Transaction_Date]],"dddd") -> Friday | D11: 19:00:48 | E11: =HOUR(Table3[[#This Row],[Transaction_Time]]) -> 19 | F11: PhonePe | G11: CUST556644 | H11: 35-44 | I11: Female | J11: Tamil Nadu | K11: Madurai | L11: JioMart | M11: Grocery | N11: Online Shopping | O11: Bank Account | P11: ICICI Bank | Q11: 612.77 | R11: 0 | S11: 0 | T11: Success | V11: Android | W11: 81 | X11: No
A12: UPI202605P2_0000011 | B12: 46151 | C12: =TEXT(Table3[[#This Row],[Transaction_Date]],"dddd") -> Saturday | D12: 19:44:27 | E12: =HOUR(Table3[[#This Row],[Transaction_Time]]) -> 19 | F12: PhonePe | G12: CUST103076 | H12: 18-24 | I12: Female | J12: Karnataka | K12: Mysuru | L12: Amazon Prime | M12: Entertainment | N12: Online Shopping | O12: Bank Account | P12: SBI | Q12: 457.86 | R12: 0 | S12: 5.23 | T12: Success | V12: Android | W12: 2 | X12: No
A13: UPI202605P2_0000012 | B13: 46149 | C13: =TEXT(Table3[[#This Row],[Transaction_Date]],"dddd") -> Thursday | D13: 13:09:13 | E13: =HOUR(Table3[[#This Row],[Transaction_Time]]) -> 13 | F13: PhonePe | G13: CUST163783 | H13: 18-24 | I13: Female | J13: Rajasthan | K13: Jodhpur | L13: BigBasket | M13: Grocery | N13: P2M | O13: Bank Account | P13: Canara Bank | Q13: 175.83 | R13: 49.99 | S13: 0 | T13: Success | V13: Android | W13: 58 | X13: No
... A48: UPI202605P2_0000047 | B48: 46152 | C48: =TEXT(Table3[[#This Row],[Transaction_Date]],"dddd") -> Sunday | D48: 13:29:33 | E48: =HOUR(Table3[[#This Row],[Transaction_Time]]) -> 13 | F48: PhonePe | G48: CUST367974 | H48: 25-34 | I48: Male | J48: Karnataka | K48: Mangaluru | L48: Tata Play | M48: Recharge & Bills | N48: P2M | O48: QR Scan | P48: HDFC Bank | Q48: 246.13 | R48: 0 | S48: 0 | T48: Success | V48: Android | W48: 10 | X48: No
A49: UPI202605P2_0000048 | B49: 46159 | C49: =TEXT(Table3[[#This Row],[Transaction_Date]],"dddd") -> Sunday | D49: 12:35:55 | E49: =HOUR(Table3[[#This Row],[Transaction_Time]]) -> 12 | F49: Paytm | G49: CUST873091 | H49: 18-24 | I49: Female | J49: Karnataka | K49: Mangaluru | L49: Broadband Bill | M49: Utilities | N49: P2M | O49: QR Scan | P49: Axis Bank | Q49: 626.93 | R49: 0 | S49: 2.1 | T49: Failed | U49: Transaction Timeout | V49: Android | W49: 26 | X49: No
A50: UPI202605P2_0000049 | B50: 46156 | C50: =TEXT(Table3[[#This Row],[Transaction_Date]],"dddd") -> Thursday | D50: 21:43:46 | E50: =HOUR(Table3[[#This Row],[Transaction_Time]]) -> 21 | F50: Amazon Pay | G50: CUST142917 | H50: 18-24 | I50: Male | J50: Tamil Nadu | K50: Coimbatore | L50: Netflix | M50: Entertainment | N50: Bill Payment | O50: QR Scan | P50: HDFC Bank | Q50: 172.82 | R50: 0 | S50: 0 | T50: Success | V50: iOS | W50: 33 | X50: No
A51: UPI202605P2_0000050 | B51: 46157 | C51: =TEXT(Table3[[#This Row],[Transaction_Date]],"dddd") -> Friday | D51: 09:56:34 | E51: =HOUR(Table3[[#This Row],[Transaction_Time]]) -> 9 | F51: PhonePe | G51: CUST630621 | H51: 18-24 | I51: Female | J51: Madhya Pradesh | K51: Jabalpur | L51: Dominos | M51: Food & Dining | N51: Wallet Transfer | O51: Mobile Number | P51: Axis Bank | Q51: 1891.52 | R51: 0 | S51: 0 | T51: Success | V51: Android | W51: 33 | X51: No
A52: UPI202605P2_0000051 | B52: 46159 | C52: =TEXT(Table3[[#This Row],[Transaction_Date]],"dddd") -> Sunday | D52: 19:49:41 | E52: =HOUR(Table3[[#This Row],[Transaction_Time]]) -> 19 | F52: PhonePe | G52: CUST245463 | H52: 25-34 | I52: Female | J52: Gujarat | K52: Ahmedabad | L52: Credit Card Bill | M52: Financial Services | N52: Bill Payment | O52: Collect Request | P52: ICICI Bank | Q52: 107.66 | R52: 0 | S52: 5.01 | T52: Success | V52: Android | W52: 62 | X52: No
A53: UPI202605P2_0000052 | B53: 46149 | C53: =TEXT(Table3[[#This Row],[Transaction_Date]],"dddd") -> Thursday | D53: 13:18:27 | E53: =HOUR(Table3[[#This Row],[Transaction_Time]]) -> 13 | F53: PhonePe | G53: CUST254011 | H53: 18-24 | I53: Male | J53: Uttar Pradesh | K53: Varanasi | L53: Gas Bill | M53: Utilities | N53: P2M | O53: QR Scan | P53: Kotak Mahindra Bank | Q53: 6623.29 | R53: 0 | S53: 0 | T53: Success | V53: Android | W53: 54 | X53: No
A54: UPI202605P2_0000053 | B54: 46151 | C54: =TEXT(Table3[[#This Row],[Transaction_Date]],"dddd") -> Saturday | D54: 10:00:46 | E54: =HOUR(Table3[[#This Row],[Transaction_Time]]) -> 10 | F54: PhonePe | G54: CUST816202 | H54: 25-34 | I54: Female | J54: Uttar Pradesh | K54: Varanasi | L54: Unacademy | M54: Education | N54: P2M | O54: UPI ID | P54: Bank of Baroda | Q54: 575.35 | R54: 42.09 | S54: 3.58 | T54: Success | V54: Android | W54: 85 | X54: No
A55: UPI202605P2_0000054 | B55: 46167 | C55: =TEXT(Table3[[#This Row],[Transaction_Date]],"dddd") -> Monday | D55: 20:16:32 | E55: =HOUR(Table3[[#This Row],[Transaction_Time]]) -> 20 | F55: PhonePe | G55: CUST479261 | H55: 45-54 | I55: Female | J55: Telangana | K55: Hyderabad | L55: Practo | M55: Healthcare | N55: Bill Payment | O55: QR Scan | P55: HDFC Bank | Q55: 51.31 | R55: 31.58 | S55: 0 | T55: Success | V55: Android | W55: 40 | X55: No
A56: UPI202605P2_0000055 | B56: 46147 | C56: =TEXT(Table3[[#This Row],[Transaction_Date]],"dddd") -> Tuesday | D56: 19:32:58 | E56: =HOUR(Table3[[#This Row],[Transaction_Time]]) -> 19 | F56: PhonePe | G56: CUST324703 | H56: 25-34 | I56: Male | J56: West Bengal | K56: Kolkata | L56: IRCTC | M56: Travel | N56: P2M | O56: Mobile Number | P56: SBI | Q56: 84.25 | R56: 0 | S56: 0 | T56: Success | V56: Android | W56: 45 | X56: No
A57: UPI202605P2_0000056 | B57: 46156 | C57: =TEXT(Table3[[#This Row],[Transaction_Date]],"dddd") -> Thursday | D57: 09:40:19 | E57: =HOUR(Table3[[#This Row],[Transaction_Time]]) -> 9 | F57: Paytm | G57: CUST941782 | H57: 18-24 | I57: Male | J57: Tamil Nadu | K57: Coimbatore | L57: Amazon Prime | M57: Entertainment | N57: P2M | O57: QR Scan | P57: SBI | Q57: 998.9 | R57: 0 | S57: 2.58 | T57: Failed | U57: Beneficiary Bank Offline | V57: iOS | W57: 97 | X57: No
A58: UPI202605P2_0000057 | B58: 46159 | C58: =TEXT(Table3[[#This Row],[Transaction_Date]],"dddd") -> Sunday | D58: 20:32:38 | E58: =HOUR(Table3[[#This Row],[Transaction_Time]]) -> 20 | F58: Google Pay | G58: CUST784614 | H58: 25-34 | I58: Female | J58: Maharashtra | K58: Mumbai | L58: Zomato | M58: Food & Dining | N58: P2M | O58: UPI ID | P58: SBI | Q58: 1454.46 | R58: 0 | S58: 0 | T58: Success | V58: Android | W58: 94 | X58: No
A59: UPI202605P2_0000058 | B59: 46162 | C59: =TEXT(Table3[[#This Row],[Transaction_Date]],"dddd") -> Wednesday | D59: 11:23:48 | E59: =HOUR(Table3[[#This Row],[Transaction_Time]]) -> 11 | F59: Google Pay | G59: CUST209130 | H59: 18-24 | I59: Male | J59: Karnataka | K59: Bengaluru | L59: Jio | M59: Recharge & Bills | N59: Wallet Transfer | O59: QR Scan | P59: Canara Bank | Q59: 895.69 | R59: 0 | S59: 7.79 | T59: Success | V59: Android | W59: 66 | X59: No
A60: UPI202605P2_0000059 | B60: 46165 | C60: =TEXT(Table3[[#This Row],[Transaction_Date]],"dddd") -> Saturday | D60: 10:49:59 | E60: =HOUR(Table3[[#This Row],[Transaction_Time]]) -> 10 | F60: PhonePe | G60: CUST105818 | H60: 25-34 | I60: Female | J60: Rajasthan | K60: Udaipur | L60: Local Kirana | M60: Grocery | N60: P2M | O60: Bank Account | P60: HDFC Bank | Q60: 311.52 | R60: 0 | S60: 4.42 | T60: Success | V60: iOS | W60: 38 | X60: No
A61: UPI202605P2_0000060 | B61: 46152 | C61: =TEXT(Table3[[#This Row],[Transaction_Date]],"dddd") -> Sunday | D61: 16:00:38 | E61: =HOUR(Table3[[#This Row],[Transaction_Time]]) -> 16 | F61: Google Pay | G61: CUST610999 | H61: 45-54 | I61: Male | J61: Rajasthan | K61: Jodhpur | L61: MSEB | M61: Recharge & Bills | N61: P2M | O61: Mobile Number | P61: Axis Bank | Q61: 743.71 | R61: 62.53 | S61: 0 | T61: Success | V61: Android | W61: 87 | X61: No
A62: UPI202605P2_0000061 | B62: 46154 | C62: =TEXT(Table3[[#This Row],[Transaction_Date]],"dddd") -> Tuesday | D62: 13:01:07 | E62: =HOUR(Table3[[#This Row],[Transaction_Time]]) -> 13 | F62: Google Pay | G62: CUST369990 | H62: 35-44 | I62: Male | J62: Delhi | K62: Rohini | L62: MedPlus | M62: Healthcare | N62: Bill Payment | O62: UPI ID | P62: Axis Bank | Q62: 643.23 | R62: 0 | S62: 5.64 | T62: Success | V62: Android | W62: 82 | X62: No
A63: UPI202605P2_0000062 | B63: 46163 | C63: =TEXT(Table3[[#This Row],[Transaction_Date]],"dddd") -> Thursday | D63: 21:56:53 | E63: =HOUR(Table3[[#This Row],[Transaction_Time]]) -> 21 | F63: Cred Pay | G63: CUST607898 | H63: 35-44 | I63: Male | J63: Rajasthan | K63: Kota | L63: MedPlus | M63: Healthcare | N63: Bill Payment | O63: Bank Account | P63: Kotak Mahindra Bank | Q63: 426.79 | R63: 0 | S63: 0 | T63: Success | V63: Android | W63: 14 | X63: No
A64: UPI202605P2_0000063 | B64: 46152 | C64: =TEXT(Table3[[#This Row],[Transaction_Date]],"dddd") -> Sunday | D64: 19:15:03 | E64: =HOUR(Table3[[#This Row],[Transaction_Time]]) -> 19 | F64: Google Pay | G64: CUST737557 | H64: 35-44 | I64: Male | J64: West Bengal | K64: Kolkata | L64: Society Maintenance | M64: Utilities | N64: Bill Payment | O64: UPI ID | P64: Kotak Mahindra Bank | Q64: 156.99 | R64: 0 | S64: 0 | T64: Success | V64: Android | W64: 14 | X64: No
A65: UPI202605P2_0000064 | B65: 46148 | C65: =TEXT(Table3[[#This Row],[Transaction_Date]],"dddd") -> Wednesday | D65: 11:36:05 | E65: =HOUR(Table3[[#This Row],[Transaction_Time]]) -> 11 | F65: PhonePe | G65: CUST347727 | H65: 25-34 | I65: Male | J65: Madhya Pradesh | K65: Bhopal | L65: Indian Oil | M65: Fuel | N65: Online Shopping | O65: UPI ID | P65: Axis Bank | Q65: 2532.54 | R65: 0 | S65: 0 | T65: Success | V65: Android | W65: 99 | X65: No
A66: UPI202605P2_0000065 | B66: 46150 | C66: =TEXT(Table3[[#This Row],[Transaction_Date]],"dddd") -> Friday | D66: 09:31:52 | E66: =HOUR(Table3[[#This Row],[Transaction_Time]]) -> 9 | F66: PhonePe | G66: CUST703894 | H66: 25-34 | I66: Female | J66: Madhya Pradesh | K66: Jabalpur | L66: Coursera | M66: Education | N66: Wallet Transfer | O66: UPI ID | P66: HDFC Bank | Q66: 339.76 | R66: 0 | S66: 1.24 | T66: Success | V66: Android | W66: 30 | X66: No
A67: UPI202605P2_0000066 | B67: 46173 | C67: =TEXT(Table3[[#This Row],[Transaction_Date]],"dddd") -> Sunday | D67: 08:48:34 | E67: =HOUR(Table3[[#This Row],[Transaction_Time]]) -> 8 | F67: PhonePe | G67: CUST105016 | H67: 18-24 | I67: Male | J67: Telangana | K67: Nizamabad | L67: Local Kirana | M67: Grocery | N67: P2P | O67: QR Scan | P67: Canara Bank | Q67: 206.55 | R67: 41.31 | S67: 0 | T67: Success | V67: Android | W67: 67 | X67: No
A68: UPI202605P2_0000067 | B68: 46144 | C68: =TEXT(Table3[[#This Row],[Transaction_Date]],"dddd") -> Saturday | D68: 19:08:42 | E68: =HOUR(Table3[[#This Row],[Transaction_Time]]) -> 19 | F68: PhonePe | G68: CUST181753 | H68: 18-24 | I68: Female | J68: West Bengal | K68: Howrah | L68: Spotify | M68: Entertainment | N68: P2P | O68: QR Scan | P68: Kotak Mahindra Bank | Q68: 508.24 | R68: 0 | S68: 0 | T68: Failed | U68: Transaction Timeout | V68: Android | W68: 91 | X68: No
A69: UPI202605P2_0000068 | B69: 46166 | C69: =TEXT(Table3[[#This Row],[Transaction_Date]],"dddd") -> Sunday | D69: 15:35:10 | E69: =HOUR(Table3[[#This Row],[Transaction_Time]]) -> 15 | F69: Google Pay | G69: CUST165329 | H69: 25-34 | I69: Female | J69: Telangana | K69: Hyderabad | L69: Society Maintenance | M69: Utilities | N69: P2M | O69: Bank Account | P69: HDFC Bank | Q69: 377.74 | R69: 0 | S69: 0 | T69: Success | V69: Android | W69: 62 | X69: No
A70: UPI202605P2_0000069 | B70: 46143 | C70: =TEXT(Table3[[#This Row],[Transaction_Date]],"dddd") -> Friday | D70: 12:55:38 | E70: =HOUR(Table3[[#This Row],[Transaction_Time]]) -> 12 | F70: PhonePe | G70: CUST536554 | H70: 35-44 | I70: Female | J70: Uttar Pradesh | K70: Lucknow | L70: Reliance Fresh | M70: Grocery | N70: Recharge | O70: UPI ID | P70: Axis Bank | Q70: 810.16 | R70: 0 | S70: 0 | T70: Success | V70: Android | W70: 41 | X70: No
A71: UPI202605P2_0000070 | B71: 46164 | C71: =TEXT(Table3[[#This Row],[Transaction_Date]],"dddd") -> Friday | D71: 14:13:59 | E71: =HOUR(Table3[[#This Row],[Transaction_Time]]) -> 14 | F71: Google Pay | G71: CUST119303 | H71: 25-34 | I71: Female | J71: Maharashtra | K71: Pune | L71: Tata Play | M71: Recharge & Bills | N71: P2P | O71: UPI ID | P71: Canara Bank | Q71: 262.07 | R71: 0 | S71: 0 | T71: Success | V71: Android | W71: 47 | X71: No
A72: UPI202605P2_0000071 | B72: 46167 | C72: =TEXT(Table3[[#This Row],[Transaction_Date]],"dddd") -> Monday | D72: 16:46:44 | E72: =HOUR(Table3[[#This Row],[Transaction_Time]]) -> 16 | F72: BHIM | G72: CUST738697 | H72: 25-34 | I72: Male | J72: Delhi | K72: New Delhi | L72: Tata Play | M72: Recharge & Bills | N72: P2P | O72: QR Scan | P72: Kotak Mahindra Bank | Q72: 328.6 | R72: 0 | S72: 0 | T72: Success | V72: Android | W72: 1 | X72: No
A73: UPI202605P2_0000072 | B73: 46166 | C73: =TEXT(Table3[[#This Row],[Transaction_Date]],"dddd") -> Sunday | D73: 11:19:25 | E73: =HOUR(Table3[[#This Row],[Transaction_Time]]) -> 11 | F73: PhonePe | G73: CUST347004 | H73: 25-34 | I73: Male | J73: Telangana | K73: Warangal | L73: Netmeds | M73: Healthcare | N73: P2M | O73: UPI ID | P73: Kotak Mahindra Bank | Q73: 382.27 | R73: 0 | S73: 1.31 | T73: Success | V73: Android | W73: 37 | X73: No
A74: UPI202605P2_0000073 | B74: 46163 | C74: =TEXT(Table3[[#This Row],[Transaction_Date]],"dddd") -> Thursday | D74: 23:41:23 | E74: =HOUR(Table3[[#This Row],[Transaction_Time]]) -> 23 | F74: Google Pay | G74: CUST470023 | H74: 35-44 | I74: Male | J74: Karnataka | K74: Hubballi | L74: Cafe Coffee Day | M74: Food & Dining | N74: P2P | O74: Collect Request | P74: Bank of Baroda | Q74: 549.83 | R74: 0 | S74: 5.16 | T74: Success | V74: iOS | W74: 99 | X74: Yes
A75: UPI202605P2_0000074 | B75: 46154 | C75: =TEXT(Table3[[#This Row],[Transaction_Date]],"dddd") -> Tuesday | D75: 14:33:28 | E75: =HOUR(Table3[[#This Row],[Transaction_Time]]) -> 14 | F75: PhonePe | G75: CUST701775 | H75: 55+ | I75: Male | J75: Delhi | K75: Dwarka | L75: Dominos | M75: Food & Dining | N75: P2P | O75: QR Scan | P75: HDFC Bank | Q75: 337.93 | R75: 0 | S75: 0 | T75: Success | V75: Android | W75: 32 | X75: No
A76: UPI202605P2_0000075 | B76: 46161 | C76: =TEXT(Table3[[#This Row],[Transaction_Date]],"dddd") -> Tuesday | D76: 10:14:04 | E76: =HOUR(Table3[[#This Row],[Transaction_Time]]) -> 10 | F76: Google Pay | G76: CUST523624 | H76: 35-44 | I76: Male | J76: Maharashtra | K76: Nashik | L76: Local Kirana | M76: Grocery | N76: Bill Payment | O76: Bank Account | P76: Canara Bank | Q76: 38.38 | R76: 0 | S76: 0 | T76: Failed | U76: Insufficient Balance | V76: Android | W76: 9 | X76: No
A77: UPI202605P2_0000076 | B77: 46157 | C77: =TEXT(Table3[[#This Row],[Transaction_Date]],"dddd") -> Friday | D77: 13:37:35 | E77: =HOUR(Table3[[#This Row],[Transaction_Time]]) -> 13 | F77: PhonePe | G77: CUST113683 | H77: 45-54 | I77: Male | J77: Madhya Pradesh | K77: Jabalpur | L77: Gas Bill | M77: Utilities | N77: Wallet Transfer | O77: Mobile Number | P77: SBI | Q77: 158.65 | R77: 0 | S77: 0 | T77: Success | V77: Android | W77: 67 | X77: No
A78: UPI202605P2_0000077 | B78: 46143 | C78: =TEXT(Table3[[#This Row],[Transaction_Date]],"dddd") -> Friday | D78: 11:14:00 | E78: =HOUR(Table3[[#This Row],[Transaction_Time]]) -> 11 | F78: PhonePe | G78: CUST402004 | H78: 35-44 | I78: Male | J78: Uttar Pradesh | K78: Kanpur | L78: Credit Card Bill | M78: Financial Services | N78: P2M | O78: Bank Account | P78: Kotak Mahindra Bank | Q78: 1415.51 | R78: 0 | S78: 0 | T78: Success | V78: Android | W78: 30 | X78: No
A79: UPI202605P2_0000078 | B79: 46152 | C79: =TEXT(Table3[[#This Row],[Transaction_Date]],"dddd") -> Sunday | D79: 09:40:03 | E79: =HOUR(Table3[[#This Row],[Transaction_Time]]) -> 9 | F79: Cred Pay | G79: CUST589630 | H79: 25-34 | I79: Male | J79: Uttar Pradesh | K79: Kanpur | L79: Netmeds | M79: Healthcare | N79: Recharge | O79: UPI ID | P79: ICICI Bank | Q79: 86.77 | R79: 6.95 | S79: 1.69 | T79: Success | V79: Android | W79: 51 | X79: No
A80: UPI202605P2_0000079 | B80: 46147 | C80: =TEXT(Table3[[#This Row],[Transaction_Date]],"dddd") -> Tuesday | D80: 11:57:02 | E80: =HOUR(Table3[[#This Row],[Transaction_Time]]) -> 11 | F80: Google Pay | G80: CUST313702 | H80: 45-54 | I80: Male | J80: Maharashtra | K80: Thane | L80: Credit Card Bill | M80: Financial Services | N80: Online Shopping | O80: QR Scan | P80: Bank of Baroda | Q80: 897.7 | R80: 0 | S80: 0 | T80: Success | V80: Android | W80: 1 | X80: No
A81: UPI202605P2_0000080 | B81: 46166 | C81: =TEXT(Table3[[#This Row],[Transaction_Date]],"dddd") -> Sunday | D81: 20:04:32 | E81: =HOUR(Table3[[#This Row],[Transaction_Time]]) -> 20 | F81: Google Pay | G81: CUST832452 | H81: 18-24 | I81: Male | J81: Karnataka | K81: Bengaluru | L81: HP Petrol Pump | M81: Fuel | N81: Subscription | O81: UPI ID | P81: Bank of Baroda | Q81: 168.85 | R81: 0 | S81: 0 | T81: Failed | U81: UPI Limit Exceeded | V81: Android | W81: 38 | X81: No
A82: UPI202605P2_0000081 | B82: 46151 | C82: =TEXT(Table3[[#This Row],[Transaction_Date]],"dddd") -> Saturday | D82: 11:42:31 | E82: =HOUR(Table3[[#This Row],[Transaction_Time]]) -> 11 | F82: Google Pay | G82: CUST223454 | H82: 25-34 | I82: Male | J82: Delhi | K82: Saket | L82: Unacademy | M82: Education | N82: P2P | O82: QR Scan | P82: ICICI Bank | Q82: 629.3 | R82: 0 | S82: 0 | T82: Pending | U82: Wrong UPI PIN | V82: iOS | W82: 72 | X82: No
A83: UPI202605P2_0000082 | B83: 46163 | C83: =TEXT(Table3[[#This Row],[Transaction_Date]],"dddd") -> Thursday | D83: 11:08:46 | E83: =HOUR(Table3[[#This Row],[Transaction_Time]]) -> 11 | F83: PhonePe | G83: CUST798588 | H83: 18-24 | I83: Male | J83: Rajasthan | K83: Udaipur | L83: Broadband Bill | M83: Utilities | N83: P2M | O83: QR Scan | P83: HDFC Bank | Q83: 2702.04 | R83: 0 | S83: 0 | T83: Success | V83: iOS | W83: 10 | X83: No
A84: UPI202605P2_0000083 | B84: 46169 | C84: =TEXT(Table3[[#This Row],[Transaction_Date]],"dddd") -> Wednesday | D84: 21:36:36 | E84: =HOUR(Table3[[#This Row],[Transaction_Time]]) -> 21 | F84: PhonePe | G84: CUST396049 | H84: 45-54 | I84: Male | J84: Telangana | K84: Hyderabad | L84: Ola | M84: Travel | N84: Bill Payment | O84: Mobile Number | P84: Bank of Baroda | Q84: 835.21 | R84: 0 | S84: 0 | T84: Success | V84: iOS | W84: 61 | X84: No
A85: UPI202605P2_0000084 | B85: 46147 | C85: =TEXT(Table3[[#This Row],[Transaction_Date]],"dddd") -> Tuesday | D85: 15:50:30 | E85: =HOUR(Table3[[#This Row],[Transaction_Time]]) -> 15 | F85: WhatsApp Pay | G85: CUST988942 | H85: 45-54 | I85: Female | J85: Tamil Nadu | K85: Salem | L85: Spotify | M85: Entertainment | N85: Bill Payment | O85: UPI ID | P85: Kotak Mahindra Bank | Q85: 727.9 | R85: 0 | S85: 6.24 | T85: Success | V85: Android | W85: 56 | X85: No
A86: UPI202605P2_0000085 | B86: 46158 | C86: =TEXT(Table3[[#This Row],[Transaction_Date]],"dddd") -> Saturday | D86: 19:12:06 | E86: =HOUR(Table3[[#This Row],[Transaction_Time]]) -> 19 | F86: Cred Pay | G86: CUST403618 | H86: 25-34 | I86: Male | J86: Karnataka | K86: Hubballi | L86: MedPlus | M86: Healthcare | N86: P2M | O86: UPI ID | P86: Kotak Mahindra Bank | Q86: 663.34 | R86: 0 | S86: 7.04 | T86: Pending | U86: Insufficient Balance | V86: Android | W86: 97 | X86: No
A87: UPI202605P2_0000086 | B87: 46165 | C87: =TEXT(Table3[[#This Row],[Transaction_Date]],"dddd") -> Saturday | D87: 09:27:22 | E87: =HOUR(Table3[[#This Row],[Transaction_Time]]) -> 9 | F87: Paytm | G87: CUST109226 | H87: 45-54 | I87: Female | J87: Telangana | K87: Nizamabad | L87: Hotstar | M87: Entertainment | N87: Online Shopping | O87: QR Scan | P87: Axis Bank | Q87: 2855.34 | R87: 0 | S87: 0 | T87: Success | V87: iOS | W87: 52 | X87: No
A88: UPI202605P2_0000087 | B88: 46157 | C88: =TEXT(Table3[[#This Row],[Transaction_Date]],"dddd") -> Friday | D88: 14:29:55 | E88: =HOUR(Table3[[#This Row],[Transaction_Time]]) -> 14 | F88: Google Pay | G88: CUST449802 | H88: 35-44 | I88: Female | J88: West Bengal | K88: Kolkata | L88: Airtel | M88: Recharge & Bills | N88: Online Shopping | O88: Collect Request | P88: HDFC Bank | Q88: 60.3 | R88: 0 | S88: 0 | T88: Success | V88: Android | W88: 96 | X88: No
A89: UPI202605P2_0000088 | B89: 46147 | C89: =TEXT(Table3[[#This Row],[Transaction_Date]],"dddd") -> Tuesday | D89: 18:43:41 | E89: =HOUR(Table3[[#This Row],[Transaction_Time]]) -> 18 | F89: Paytm | G89: CUST368650 | H89: 55+ | I89: Female | J89: Uttar Pradesh | K89: Lucknow | L89: Ola | M89: Travel | N89: Bill Payment | O89: Mobile Number | P89: HDFC Bank | Q89: 531.13 | R89: 0 | S89: 0 | T89: Success | V89: Android | W89: 62 | X89: No
A90: UPI202605P2_0000089 | B90: 46173 | C90: =TEXT(Table3[[#This Row],[Transaction_Date]],"dddd") -> Sunday | D90: 22:06:03 | E90: =HOUR(Table3[[#This Row],[Transaction_Time]]) -> 22 | F90: PhonePe | G90: CUST733499 | H90: 18-24 | I90: Male | J90: Maharashtra | K90: Thane | L90: Ajio | M90: Shopping | N90: P2M | O90: QR Scan | P90: HDFC Bank | Q90: 829.4 | R90: 0 | S90: 0 | T90: Success | V90: Android | W90: 56 | X90: No
A91: UPI202605P2_0000090 | B91: 46165 | C91: =TEXT(Table3[[#This Row],[Transaction_Date]],"dddd") -> Saturday | D91: 14:21:51 | E91: =HOUR(Table3[[#This Row],[Transaction_Time]]) -> 14 | F91: PhonePe | G91: CUST637096 | H91: 25-34 | I91: Female | J91: Uttar Pradesh | K91: Kanpur | L91: Tata Play | M91: Recharge & Bills | N91: P2P | O91: UPI ID | P91: Kotak Mahindra Bank | Q91: 161.82 | R91: 0 | S91: 0 | T91: Failed | U91: Beneficiary Bank Offline | V91: Android | W91: 70 | X91: No
A92: UPI202605P2_0000091 | B92: 46150 | C92: =TEXT(Table3[[#This Row],[Transaction_Date]],"dddd") -> Friday | D92: 20:15:12 | E92: =HOUR(Table3[[#This Row],[Transaction_Time]]) -> 20 | F92: PhonePe | G92: CUST230782 | H92: 35-44 | I92: Male | J92: Rajasthan | K92: Kota | L92: Insurance Premium | M92: Financial Services | N92: P2M | O92: Collect Request | P92: Canara Bank | Q92: 26.51 | R92: 0 | S92: 0 | T92: Success | V92: Android | W92: 66 | X92: No
A93: UPI202605P2_0000092 | B93: 46167 | C93: =TEXT(Table3[[#This Row],[Transaction_Date]],"dddd") -> Monday | D93: 11:28:08 | E93: =HOUR(Table3[[#This Row],[Transaction_Time]]) -> 11 | F93: PhonePe | G93: CUST812136 | H93: 18-24 | I93: Male | J93: West Bengal | K93: Howrah | L93: Water Bill | M93: Utilities | N93: P2M | O93: UPI ID | P93: Bank of Baroda | Q93: 448.54 | R93: 0 | S93: 0 | T93: Success | V93: Android | W93: 57 | X93: No
A94: UPI202605P2_0000093 | B94: 46167 | C94: =TEXT(Table3[[#This Row],[Transaction_Date]],"dddd") -> Monday | D94: 14:17:29 | E94: =HOUR(Table3[[#This Row],[Transaction_Time]]) -> 14 | F94: PhonePe | G94: CUST550042 | H94: 35-44 | I94: Male | J94: Rajasthan | K94: Jodhpur | L94: Broadband Bill | M94: Utilities | N94: Recharge | O94: UPI ID | P94: HDFC Bank | Q94: 658.36 | R94: 0 | S94: 0 | T94: Success | V94: Android | W94: 19 | X94: No
A95: UPI202605P2_0000094 | B95: 46156 | C95: =TEXT(Table3[[#This Row],[Transaction_Date]],"dddd") -> Thursday | D95: 12:59:04 | E95: =HOUR(Table3[[#This Row],[Transaction_Time]]) -> 12 | F95: Google Pay | G95: CUST875203 | H95: 55+ | I95: Male | J95: Maharashtra | K95: Pune | L95: Reliance Fresh | M95: Grocery | N95: P2P | O95: Bank Account | P95: Kotak Mahindra Bank | Q95: 208 | R95: 0 | S95: 0 | T95: Success | V95: Android | W95: 61 | X95: No
A96: UPI202605P2_0000095 | B96: 46169 | C96: =TEXT(Table3[[#This Row],[Transaction_Date]],"dddd") -> Wednesday | D96: 15:55:54 | E96: =HOUR(Table3[[#This Row],[Transaction_Time]]) -> 15 | F96: PhonePe | G96: CUST199339 | H96: 55+ | I96: Other | J96: Karnataka | K96: Bengaluru | L96: Vi | M96: Recharge & Bills | N96: P2P | O96: UPI ID | P96: ICICI Bank | Q96: 670.02 | R96: 0 | S96: 0 | T96: Success | V96: Android | W96: 35 | X96: No
A97: UPI202605P2_0000096 | B97: 46170 | C97: =TEXT(Table3[[#This Row],[Transaction_Date]],"dddd") -> Thursday | D97: 16:03:41 | E97: =HOUR(Table3[[#This Row],[Transaction_Time]]) -> 16 | F97: PhonePe | G97: CUST843931 | H97: 25-34 | I97: Female | J97: Rajasthan | K97: Jaipur | L97: BigBasket | M97: Grocery | N97: Recharge | O97: Collect Request | P97: Kotak Mahindra Bank | Q97: 265.59 | R97: 0 | S97: 0 | T97: Success | V97: Android | W97: 72 | X97: No
A98: UPI202605P2_0000097 | B98: 46171 | C98: =TEXT(Table3[[#This Row],[Transaction_Date]],"dddd") -> Friday | D98: 23:53:00 | E98: =HOUR(Table3[[#This Row],[Transaction_Time]]) -> 23 | F98: PhonePe | G98: CUST621314 | H98: 18-24 | I98: Male | J98: Gujarat | K98: Vadodara | L98: Flipkart | M98: Shopping | N98: Bill Payment | O98: Mobile Number | P98: SBI | Q98: 1847.36 | R98: 0 | S98: 0 | T98: Success | V98: Android | W98: 63 | X98: No
A99: UPI202605P2_0000098 | B99: 46172 | C99: =TEXT(Table3[[#This Row],[Transaction_Date]],"dddd") -> Saturday | D99: 21:59:48 | E99: =HOUR(Table3[[#This Row],[Transaction_Time]]) -> 21 | F99: Paytm | G99: CUST896719 | H99: 45-54 | I99: Male | J99: Karnataka | K99: Mangaluru | L99: Amazon Prime | M99: Entertainment | N99: Online Shopping | O99: UPI ID | P99: ICICI Bank | Q99: 99.4 | R99: 0 | S99: 0 | T99: Success | V99: Android | W99: 32 | X99: No
A100: UPI202605P2_0000099 | B100: 46164 | C100: =TEXT(Table3[[#This Row],[Transaction_Date]],"dddd") -> Friday | D100: 20:10:26 | E100: =HOUR(Table3[[#This Row],[Transaction_Time]]) -> 20 | F100: Cred Pay | G100: CUST246560 | H100: 18-24 | I100: Male | J100: Karnataka | K100: Mangaluru | L100: Ajio | M100: Shopping | N100: P2P | O100: Mobile Number | P100: HDFC Bank | Q100: 659.07 | R100: 0 | S100: 0 | T100: Success | V100: Android | W100: 53 | X100: No
A101: UPI202605P2_0000100 | B101: 46160 | C101: =TEXT(Table3[[#This Row],[Transaction_Date]],"dddd") -> Monday | D101: 15:13:55 | E101: =HOUR(Table3[[#This Row],[Transaction_Time]]) -> 15 | F101: Paytm | G101: CUST725727 | H101: 25-34 | I101: Male | J101: Karnataka | K101: Bengaluru | L101: Broadband Bill | M101: Utilities | N101: Online Shopping | O101: UPI ID | P101: Axis Bank | Q101: 494.85 | R101: 1.16 | S101: 6.29 | T101: Success | V101: iOS | W101: 70 | X101: No
A102: UPI202605P2_0000101 | B102: 46157 | C102: =TEXT(Table3[[#This Row],[Transaction_Date]],"dddd") -> Friday | D102: 14:03:10 | E102: =HOUR(Table3[[#This Row],[Transaction_Time]]) -> 14 | F102: Google Pay | G102: CUST529841 | H102: 35-44 | I102: Male | J102: Uttar Pradesh | K102: Noida | L102: Amazon | M102: Shopping | N102: Online Shopping | O102: UPI ID | P102: Bank of Baroda | Q102: 129.25 | R102: 0 | S102: 0 | T102: Success | V102: iOS | W102: 95 | X102: No
A103: UPI202605P2_0000102 | B103: 46164 | C103: =TEXT(Table3[[#This Row],[Transaction_Date]],"dddd") -> Friday | D103: 13:24:16 | E103: =HOUR(Table3[[#This Row],[Transaction_Time]]) -> 13 | F103: Paytm | G103: CUST774805 | H103: 25-34 | I103: Female | J103: Delhi | K103: Rohini | L103: Netflix | M103: Entertainment | N103: P2P | O103: UPI ID | P103: HDFC Bank | Q103: 550.04 | R103: 0 | S103: 0 | T103: Success | V103: iOS | W103: 65 | X103: No
... A105: UPI202605P2_0000104 | B105: 46153 | C105: =TEXT(Table3[[#This Row],[Transaction_Date]],"dddd") -> Monday | D105: 12:44:46 | E105: =HOUR(Table3[[#This Row],[Transaction_Time]]) -> 12 | F105: Paytm | G105: CUST929948 | H105: 35-44 | I105: Female | J105: Rajasthan | K105: Jodhpur | L105: Netflix | M105: Entertainment | N105: P2P | O105: QR Scan | P105: Axis Bank | Q105: 287.14 | R105: 0 | S105: 0 | T105: Success | V105: Android | W105: 27 | X105: No
A106: UPI202605P2_0000105 | B106: 46154 | C106: =TEXT(Table3[[#This Row],[Transaction_Date]],"dddd") -> Tuesday | D106: 23:35:42 | E106: =HOUR(Table3[[#This Row],[Transaction_Time]]) -> 23 | F106: Google Pay | G106: CUST618593 | H106: 25-34 | I106: Female | J106: Gujarat | K106: Ahmedabad | L106: Mutual Fund SIP | M106: Financial Services | N106: P2M | O106: QR Scan | P106: HDFC Bank | Q106: 1575.83 | R106: 0 | S106: 0 | T106: Pending | U106: Beneficiary Bank Offline | V106: iOS | W106: 35 | X106: No
A107: UPI202605P2_0000106 | B107: 46148 | C107: =TEXT(Table3[[#This Row],[Transaction_Date]],"dddd") -> Wednesday | D107: 18:09:12 | E107: =HOUR(Table3[[#This Row],[Transaction_Time]]) -> 18 | F107: PhonePe | G107: CUST250743 | H107: 35-44 | I107: Male | J107: Rajasthan | K107: Jaipur | L107: Broadband Bill | M107: Utilities | N107: P2P | O107: QR Scan | P107: HDFC Bank | Q107: 133.82 | R107: 0 | S107: 0 | T107: Success | V107: Android | W107: 66 | X107: No
A108: UPI202605P2_0000107 | B108: 46172 | C108: =TEXT(Table3[[#This Row],[Transaction_Date]],"dddd") -> Saturday | D108: 12:03:37 | E108: =HOUR(Table3[[#This Row],[Transaction_Time]]) -> 12 | F108: PhonePe | G108: CUST667280 | H108: 25-34 | I108: Female | J108: West Bengal | K108: Kolkata | L108: Cafe Coffee Day | M108: Food & Dining | N108: P2M | O108: QR Scan | P108: Axis Bank | Q108: 533.24 | R108: 0 | S108: 2.5 | T108: Failed | U108: Bank Server Down | V108: Android | W108: 41 | X108: No
A109: UPI202605P2_0000108 | B109: 46150 | C109: =TEXT(Table3[[#This Row],[Transaction_Date]],"dddd") -> Friday | D109: 18:03:47 | E109: =HOUR(Table3[[#This Row],[Transaction_Time]]) -> 18 | F109: Amazon Pay | G109: CUST606864 | H109: 45-54 | I109: Male | J109: Tamil Nadu | K109: Madurai | L109: Shell Fuel | M109: Fuel | N109: P2P | O109: Mobile Number | P109: SBI | Q109: 494.41 | R109: 58.09 | S109: 0 | T109: Success | V109: iOS | W109: 58 | X109: No
A110: UPI202605P2_0000109 | B110: 46171 | C110: =TEXT(Table3[[#This Row],[Transaction_Date]],"dddd") -> Friday | D110: 12:03:37 | E110: =HOUR(Table3[[#This Row],[Transaction_Time]]) -> 12 | F110: WhatsApp Pay | G110: CUST911519 | H110: 18-24 | I110: Male | J110: Delhi | K110: New Delhi | L110: RedBus | M110: Travel | N110: P2P | O110: QR Scan | P110: Kotak Mahindra Bank | Q110: 677.42 | R110: 0 | S110: 0 | T110: Success | V110: iOS | W110: 86 | X110: No
A111: UPI202605P2_0000110 | B111: 46157 | C111: =TEXT(Table3[[#This Row],[Transaction_Date]],"dddd") -> Friday | D111: 15:58:54 | E111: =HOUR(Table3[[#This Row],[Transaction_Time]]) -> 15 | F111: PhonePe | G111: CUST229572 | H111: 25-34 | I111: Female | J111: Rajasthan | K111: Udaipur | L111: BigBasket | M111: Grocery | N111: P2M | O111: Bank Account | P111: Kotak Mahindra Bank | Q111: 963.22 | R111: 0 | S111: 0 | T111: Success | V111: Android | W111: 22 | X111: No
A112: UPI202605P2_0000111 | B112: 46151 | C112: =TEXT(Table3[[#This Row],[Transaction_Date]],"dddd") -> Saturday | D112: 16:03:32 | E112: =HOUR(Table3[[#This Row],[Transaction_Time]]) -> 16 | F112: BHIM | G112: CUST936269 | H112: 55+ | I112: Female | J112: Uttar Pradesh | K112: Kanpur | L112: Gas Bill | M112: Utilities | N112: P2M | O112: UPI ID | P112: Bank of Baroda | Q112: 535.55 | R112: 70.83 | S112: 0 | T112: Success | V112: Android | W112: 95 | X112: No
A113: UPI202605P2_0000112 | B113: 46144 | C113: =TEXT(Table3[[#This Row],[Transaction_Date]],"dddd") -> Saturday | D113: 09:11:04 | E113: =HOUR(Table3[[#This Row],[Transaction_Time]]) -> 9 | F113: PhonePe | G113: CUST576794 | H113: 35-44 | I113: Male | J113: Tamil Nadu | K113: Coimbatore | L113: Ola | M113: Travel | N113: P2P | O113: Bank Account | P113: ICICI Bank | Q113: 77.95 | R113: 0 | S113: 0 | T113: Success | V113: Android | W113: 41 | X113: No
A114: UPI202605P2_0000113 | B114: 46156 | C114: =TEXT(Table3[[#This Row],[Transaction_Date]],"dddd") -> Thursday | D114: 17:43:55 | E114: =HOUR(Table3[[#This Row],[Transaction_Time]]) -> 17 | F114: Amazon Pay | G114: CUST223524 | H114: 35-44 | I114: Male | J114: Madhya Pradesh | K114: Indore | L114: Electricity Board | M114: Recharge & Bills | N114: Subscription | O114: UPI ID | P114: SBI | Q114: 380.63 | R114: 0 | S114: 0 | T114: Success | V114: Android | W114: 68 | X114: No
A115: UPI202605P2_0000114 | B115: 46157 | C115: =TEXT(Table3[[#This Row],[Transaction_Date]],"dddd") -> Friday | D115: 11:07:56 | E115: =HOUR(Table3[[#This Row],[Transaction_Time]]) -> 11 | F115: BHIM | G115: CUST489948 | H115: 25-34 | I115: Male | J115: Rajasthan | K115: Udaipur | L115: MakeMyTrip | M115: Travel | N115: P2M | O115: UPI ID | P115: SBI | Q115: 493.07 | R115: 48.05 | S115: 0 | T115: Success | V115: Android | W115: 90 | X115: No
A116: UPI202605P2_0000115 | B116: 46156 | C116: =TEXT(Table3[[#This Row],[Transaction_Date]],"dddd") -> Thursday | D116: 17:37:38 | E116: =HOUR(Table3[[#This Row],[Transaction_Time]]) -> 17 | F116: PhonePe | G116: CUST651649 | H116: 25-34 | I116: Male | J116: Rajasthan | K116: Jaipur | L116: Amazon | M116: Shopping | N116: Online Shopping | O116: UPI ID | P116: Canara Bank | Q116: 550.43 | R116: 0 | S116: 0 | T116: Success | V116: Android | W116: 83 | X116: No
A117: UPI202605P2_0000116 | B117: 46162 | C117: =TEXT(Table3[[#This Row],[Transaction_Date]],"dddd") -> Wednesday | D117: 08:05:26 | E117: =HOUR(Table3[[#This Row],[Transaction_Time]]) -> 8 | F117: PhonePe | G117: CUST989457 | H117: 45-54 | I117: Female | J117: Tamil Nadu | K117: Madurai | L117: Swiggy | M117: Food & Dining | N117: P2M | O117: Bank Account | P117: Axis Bank | Q117: 272.45 | R117: 0 | S117: 0 | T117: Success | V117: Android | W117: 20 | X117: No
A118: UPI202605P2_0000117 | B118: 46164 | C118: =TEXT(Table3[[#This Row],[Transaction_Date]],"dddd") -> Friday | D118: 18:36:33 | E118: =HOUR(Table3[[#This Row],[Transaction_Time]]) -> 18 | F118: WhatsApp Pay | G118: CUST929968 | H118: 25-34 | I118: Female | J118: Karnataka | K118: Mysuru | L118: Jio | M118: Recharge & Bills | N118: Bill Payment | O118: UPI ID | P118: Kotak Mahindra Bank | Q118: 2753.2 | R118: 0 | S118: 0 | T118: Success | V118: Android | W118: 74 | X118: No
A119: UPI202605P2_0000118 | B119: 46145 | C119: =TEXT(Table3[[#This Row],[Transaction_Date]],"dddd") -> Sunday | D119: 12:16:13 | E119: =HOUR(Table3[[#This Row],[Transaction_Time]]) -> 12 | F119: WhatsApp Pay | G119: CUST340075 | H119: 25-34 | I119: Female | J119: Rajasthan | K119: Jodhpur | L119: McDonalds | M119: Food & Dining | N119: Bill Payment | O119: UPI ID | P119: ICICI Bank | Q119: 772.66 | R119: 0 | S119: 0 | T119: Success | V119: Android | W119: 40 | X119: No
A120: UPI202605P2_0000119 | B120: 46173 | C120: =TEXT(Table3[[#This Row],[Transaction_Date]],"dddd") -> Sunday | D120: 18:20:15 | E120: =HOUR(Table3[[#This Row],[Transaction_Time]]) -> 18 | F120: PhonePe | G120: CUST759064 | H120: 25-34 | I120: Male | J120: Maharashtra | K120: Mumbai | L120: Local Kirana | M120: Grocery | N120: P2M | O120: Bank Account | P120: HDFC Bank | Q120: 1908.07 | R120: 0 | S120: 5.03 | T120: Success | V120: Android | W120: 50 | X120: No
... A124: UPI202605P2_0000123 | B124: 46170 | C124: =TEXT(Table3[[#This Row],[Transaction_Date]],"dddd") -> Thursday | D124: 05:39:36 | E124: =HOUR(Table3[[#This Row],[Transaction_Time]]) -> 5 | F124: Google Pay | G124: CUST148441 | H124: 35-44 | I124: Male | J124: Telangana | K124: Nizamabad | L124: Loan EMI | M124: Financial Services | N124: Online Shopping | O124: Collect Request | P124: HDFC Bank | Q124: 3310.4 | R124: 0 | S124: 0.4 | T124: Success | V124: Android | W124: 12 | X124: No
A125: UPI202605P2_0000124 | B125: 46162 | C125: =TEXT(Table3[[#This Row],[Transaction_Date]],"dddd") -> Wednesday | D125: 23:04:34 | E125: =HOUR(Table3[[#This Row],[Transaction_Time]]) -> 23 | F125: PhonePe | G125: CUST818896 | H125: 25-34 | I125: Male | J125: Maharashtra | K125: Nagpur | L125: Airtel | M125: Recharge & Bills | N125: P2M | O125: QR Scan | P125: HDFC Bank | Q125: 1625.01 | R125: 0 | S125: 0 | T125: Failed | U125: Insufficient Balance | V125: Android | W125: 97 | X125: No
A126: UPI202605P2_0000125 | B126: 46144 | C126: =TEXT(Table3[[#This Row],[Transaction_Date]],"dddd") -> Saturday | D126: 11:16:08 | E126: =HOUR(Table3[[#This Row],[Transaction_Time]]) -> 11 | F126: Google Pay | G126: CUST142173 | H126: 35-44 | I126: Male | J126: Uttar Pradesh | K126: Noida | L126: MakeMyTrip | M126: Travel | N126: P2P | O126: QR Scan | P126: ICICI Bank | Q126: 666.92 | R126: 0 | S126: 0 | T126: Failed | U126: Transaction Timeout | V126: Android | W126: 5 | X126: No
A127: UPI202605P2_0000126 | B127: 46171 | C127: =TEXT(Table3[[#This Row],[Transaction_Date]],"dddd") -> Friday | D127: 21:56:04 | E127: =HOUR(Table3[[#This Row],[Transaction_Time]]) -> 21 | F127: PhonePe | G127: CUST545615 | H127: 35-44 | I127: Male | J127: Tamil Nadu | K127: Coimbatore | L127: Local Clinic | M127: Healthcare | N127: P2M | O127: UPI ID | P127: Axis Bank | Q127: 492.28 | R127: 0 | S127: 0 | T127: Failed | U127: Bank Server Down | V127: Android | W127: 64 | X127: No
A128: UPI202605P2_0000127 | B128: 46163 | C128: =TEXT(Table3[[#This Row],[Transaction_Date]],"dddd") -> Thursday | D128: 20:23:18 | E128: =HOUR(Table3[[#This Row],[Transaction_Time]]) -> 20 | F128: Google Pay | G128: CUST750094 | H128: 35-44 | I128: Female | J128: Karnataka | K128: Hubballi | L128: Zomato | M128: Food & Dining | N128: Bill Payment | O128: QR Scan | P128: Bank of Baroda | Q128: 744.31 | R128: 0 | S128: 6.29 | T128: Success | V128: Android | W128: 63 | X128: No
A129: UPI202605P2_0000128 | B129: 46156 | C129: =TEXT(Table3[[#This Row],[Transaction_Date]],"dddd") -> Thursday | D129: 10:53:34 | E129: =HOUR(Table3[[#This Row],[Transaction_Time]]) -> 10 | F129: Google Pay | G129: CUST264162 | H129: 25-34 | I129: Female | J129: Tamil Nadu | K129: Coimbatore | L129: Gas Bill | M129: Utilities | N129: P2P | O129: QR Scan | P129: Canara Bank | Q129: 3406.36 | R129: 0 | S129: 0 | T129: Success | V129: Android | W129: 37 | X129: No
A130: UPI202605P2_0000129 | B130: 46147 | C130: =TEXT(Table3[[#This Row],[Transaction_Date]],"dddd") -> Tuesday | D130: 18:39:51 | E130: =HOUR(Table3[[#This Row],[Transaction_Time]]) -> 18 | F130: PhonePe | G130: CUST881081 | H130: 35-44 | I130: Female | J130: Karnataka | K130: Mangaluru | L130: McDonalds | M130: Food & Dining | N130: P2M | O130: Mobile Number | P130: ICICI Bank | Q130: 287.78 | R130: 0 | S130: 4.31 | T130: Success | V130: Android | W130: 53 | X130: No
A131: UPI202605P2_0000130 | B131: 46171 | C131: =TEXT(Table3[[#This Row],[Transaction_Date]],"dddd") -> Friday | D131: 18:00:42 | E131: =HOUR(Table3[[#This Row],[Transaction_Time]]) -> 18 | F131: Google Pay | G131: CUST987905 | H131: 45-54 | I131: Male | J131: Tamil Nadu | K131: Salem | L131: Udemy | M131: Education | N131: Bill Payment | O131: Bank Account | P131: Axis Bank | Q131: 689.86 | R131: 0 | S131: 0 | T131: Pending | U131: Insufficient Balance | V131: Android | W131: 82 | X131: No
A132: UPI202605P2_0000131 | B132: 46164 | C132: =TEXT(Table3[[#This Row],[Transaction_Date]],"dddd") -> Friday | D132: 19:19:59 | E132: =HOUR(Table3[[#This Row],[Transaction_Time]]) -> 19 | F132: Paytm | G132: CUST602328 | H132: 18-24 | I132: Male | J132: Madhya Pradesh | K132: Gwalior | L132: Topmate | M132: Education | N132: Online Shopping | O132: Bank Account | P132: HDFC Bank | Q132: 714.59 | R132: 0 | S132: 6.25 | T132: Success | V132: Android | W132: 100 | X132: No
A133: UPI202605P2_0000132 | B133: 46152 | C133: =TEXT(Table3[[#This Row],[Transaction_Date]],"dddd") -> Sunday | D133: 18:56:08 | E133: =HOUR(Table3[[#This Row],[Transaction_Time]]) -> 18 | F133: Google Pay | G133: CUST485696 | H133: 35-44 | I133: Female | J133: Rajasthan | K133: Kota | L133: Dmart | M133: Grocery | N133: P2M | O133: Mobile Number | P133: SBI | Q133: 455.55 | R133: 0 | S133: 0 | T133: Pending | U133: Insufficient Balance | V133: iOS | W133: 41 | X133: No
A134: UPI202605P2_0000133 | B134: 46152 | C134: =TEXT(Table3[[#This Row],[Transaction_Date]],"dddd") -> Sunday | D134: 12:56:06 | E134: =HOUR(Table3[[#This Row],[Transaction_Time]]) -> 12 | F134: PhonePe | G134: CUST965017 | H134: 25-34 | I134: Female | J134: Tamil Nadu | K134: Madurai | L134: Spotify | M134: Entertainment | N134: P2M | O134: QR Scan | P134: SBI | Q134: 227.89 | R134: 0 | S134: 0 | T134: Success | V134: Android | W134: 73 | X134: No
A135: UPI202605P2_0000134 | B135: 46164 | C135: =TEXT(Table3[[#This Row],[Transaction_Date]],"dddd") -> Friday | D135: 19:09:17 | E135: =HOUR(Table3[[#This Row],[Transaction_Time]]) -> 19 | F135: Google Pay | G135: CUST968984 | H135: 25-34 | I135: Male | J135: Uttar Pradesh | K135: Kanpur | L135: Water Bill | M135: Utilities | N135: Subscription | O135: UPI ID | P135: Axis Bank | Q135: 135.99 | R135: 0 | S135: 0 | T135: Success | V135: Android | W135: 47 | X135: No
A136: UPI202605P2_0000135 | B136: 46148 | C136: =TEXT(Table3[[#This Row],[Transaction_Date]],"dddd") -> Wednesday | D136: 12:13:45 | E136: =HOUR(Table3[[#This Row],[Transaction_Time]]) -> 12 | F136: Cred Pay | G136: CUST837147 | H136: 18-24 | I136: Female | J136: Telangana | K136: Warangal | L136: Credit Card Bill | M136: Financial Services | N136: Bill Payment | O136: Collect Request | P136: ICICI Bank | Q136: 393.69 | R136: 0 | S136: 0 | T136: Success | V136: Android | W136: 85 | X136: No
A137: UPI202605P2_0000136 | B137: 46170 | C137: =TEXT(Table3[[#This Row],[Transaction_Date]],"dddd") -> Thursday | D137: 13:43:40 | E137: =HOUR(Table3[[#This Row],[Transaction_Time]]) -> 13 | F137: PhonePe | G137: CUST570211 | H137: 35-44 | I137: Female | J137: Tamil Nadu | K137: Coimbatore | L137: Reliance Fresh | M137: Grocery | N137: Bill Payment | O137: QR Scan | P137: HDFC Bank | Q137: 591.76 | R137: 0 | S137: 0 | T137: Success | V137: Android | W137: 18 | X137: No
A138: UPI202605P2_0000137 | B138: 46170 | C138: =TEXT(Table3[[#This Row],[Transaction_Date]],"dddd") -> Thursday | D138: 20:32:31 | E138: =HOUR(Table3[[#This Row],[Transaction_Time]]) -> 20 | F138: Google Pay | G138: CUST366963 | H138: 25-34 | I138: Male | J138: Delhi | K138: Saket | L138: Insurance Premium | M138: Financial Services | N138: Recharge | O138: UPI ID | P138: Axis Bank | Q138: 789.35 | R138: 55.54 | S138: 0 | T138: Success | V138: Android | W138: 40 | X138: No
...

Sheet Dashboard

Sheet pivot table
A3: Count of Transaction_ID | B3: Sum of Amount_INR | C3: Sum of Cashback_INR
A4: 5000 | B4: 4225721.7 | C4: 33561.75
A6: =GETPIVOTDATA("Count of Transaction_ID",$A$3) -> 5000 | B6: =GETPIVOTDATA("Sum of Amount_INR",$A$3) -> 4225721.7 | C6: =GETPIVOTDATA("Sum of Cashback_INR",$A$3) -> 33561.75
B7: =B6/1000000 -> 4.2257217 | C7: =C6/10000 -> 3.356175
A11: Row Labels | B11: Count of Transaction_ID
A12: Failed | B12: 339
A13: Pending | B13: 115
A14: Success | B14: 4546 | C14: =GETPIVOTDATA("Transaction_ID",$A$11,"Status","Success") -> 4546 | D14: =C14/A6 -> 0.9092
A15: Grand Total | B15: 5000
A18: Row Labels | B18: Count of Transaction_ID
A19: No | B19: 4856
A20: Yes | B20: 144 | C20: =GETPIVOTDATA("Transaction_ID",$A$18,"Is_Suspected_Fraud","Yes") -> 144
A21: Grand Total | B21: 5000
A24: Row Labels | B24: Sum of Amount_INR
A25: 46143 | B25: 128206.46 | D25: Day | E25: Amount | F25: Amount 1
A26: 46144 | B26: 141034.66 | D26: =DAY(A25) -> 1 | E26: =GETPIVOTDATA("Amount_INR",$A$24,"Transaction_Date",A25)/100000 -> 1.2820646 | F26: =GETPIVOTDATA("Amount_INR",$A$24,"Transaction_Date",A25)/100000 -> 1.2820646
A27: 46145 | B27: 134058.36 | D27: =DAY(A26) -> 2 | E27: =GETPIVOTDATA("Amount_INR",$A$24,"Transaction_Date",A26)/100000 -> 1.4103466 | F27: =GETPIVOTDATA("Amount_INR",$A$24,"Transaction_Date",A26)/100000 -> 1.4103466
A28: 46146 | B28: 147248.15 | D28: =DAY(A27) -> 3 | E28: =GETPIVOTDATA("Amount_INR",$A$24,"Transaction_Date",A27)/100000 -> 1.3405836 | F28: =GETPIVOTDATA("Amount_INR",$A$24,"Transaction_Date",A27)/100000 -> 1.3405836
A29: 46147 | B29: 133180.76 | D29: =DAY(A28) -> 4 | E29: =GETPIVOTDATA("Amount_INR",$A$24,"Transaction_Date",A28)/100000 -> 1.4724815 | F29: =GETPIVOTDATA("Amount_INR",$A$24,"Transaction_Date",A28)/100000 -> 1.4724815
A30: 46148 | B30: 138179.21 | D30: =DAY(A29) -> 5 | E30: =GETPIVOTDATA("Amount_INR",$A$24,"Transaction_Date",A29)/100000 -> 1.3318076 | F30: =GETPIVOTDATA("Amount_INR",$A$24,"Transaction_Date",A29)/100000 -> 1.3318076
A31: 46149 | B31: 145328.88 | D31: =DAY(A30) -> 6 | E31: =GETPIVOTDATA("Amount_INR",$A$24,"Transaction_Date",A30)/100000 -> 1.3817921 | F31: =GETPIVOTDATA("Amount_INR",$A$24,"Transaction_Date",A30)/100000 -> 1.3817921
A32: 46150 | B32: 129567.08 | D32: =DAY(A31) -> 7 | E32: =GETPIVOTDATA("Amount_INR",$A$24,"Transaction_Date",A31)/100000 -> 1.4532888 | F32: =GETPIVOTDATA("Amount_INR",$A$24,"Transaction_Date",A31)/100000 -> 1.4532888
A33: 46151 | B33: 165348.89 | D33: =DAY(A32) -> 8 | E33: =GETPIVOTDATA("Amount_INR",$A$24,"Transaction_Date",A32)/100000 -> 1.2956708 | F33: =GETPIVOTDATA("Amount_INR",$A$24,"Transaction_Date",A32)/100000 -> 1.2956708
A34: 46152 | B34: 122855.69 | D34: =DAY(A33) -> 9 | E34: =GETPIVOTDATA("Amount_INR",$A$24,"Transaction_Date",A33)/100000 -> 1.6534889 | F34: =GETPIVOTDATA("Amount_INR",$A$24,"Transaction_Date",A33)/100000 -> 1.6534889
A35: 46153 | B35: 123097.25 | D35: =DAY(A34) -> 10 | E35: =GETPIVOTDATA("Amount_INR",$A$24,"Transaction_Date",A34)/100000 -> 1.2285569 | F35: =GETPIVOTDATA("Amount_INR",$A$24,"Transaction_Date",A34)/100000 -> 1.2285569
A36: 46154 | B36: 120525.93 | D36: =DAY(A35) -> 11 | E36: =GETPIVOTDATA("Amount_INR",$A$24,"Transaction_Date",A35)/100000 -> 1.2309725 | F36: =GETPIVOTDATA("Amount_INR",$A$24,"Transaction_Date",A35)/100000 -> 1.2309725
A37: 46155 | B37: 120124.95 | D37: =DAY(A36) -> 12 | E37: =GETPIVOTDATA("Amount_INR",$A$24,"Transaction_Date",A36)/100000 -> 1.2052593 | F37: =GETPIVOTDATA("Amount_INR",$A$24,"Transaction_Date",A36)/100000 -> 1.2052593
... A55: 46173 | B55: 152703.4 | D55: =DAY(A54) -> 30 | E55: =GETPIVOTDATA("Amount_INR",$A$24,"Transaction_Date",A54)/100000 -> 1.1934783 | F55: =GETPIVOTDATA("Amount_INR",$A$24,"Transaction_Date",A54)/100000 -> 1.1934783
A56: Grand Total | B56: 4225721.7 | D56: =DAY(A55) -> 31 | E56: =GETPIVOTDATA("Amount_INR",$A$24,"Transaction_Date",A55)/100000 -> 1.527034 | F56: =GETPIVOTDATA("Amount_INR",$A$24,"Transaction_Date",A55)/100000 -> 1.527034
A60: Row Labels | B60: Sum of Amount_INR
A61: Amazon Pay | B61: 260802.52
A62: BHIM | B62: 158520.99
A63: Cred Pay | B63: 134492.88
A64: Google Pay | B64: 920905.9
A65: Paytm | B65: 637060.75
A66: PhonePe | B66: 2006465.7
A67: WhatsApp Pay | B67: 107473.02
A72: Row Labels | B72: Sum of Amount_INR
A73: PhonePe | B73: 0.474822
A74: Google Pay | B74: 0.21792867
A75: Paytm | B75: 0.15075786
A76: Amazon Pay | B76: 0.061717865
A77: BHIM | B77: 0.037513353
A78: Cred Pay | B78: 0.031827198
A79: WhatsApp Pay | B79: 0.025433057
A82: Row Labels | B82: Sum of Amount_INR
A83: Success | B83: 0.90920187
A84: Failed | B84: 0.070434371
A85: Pending | B85: 0.020363764
A89: Row Labels | B89: Sum of Amount_INR | D89: state | E89: amount
A90: Tamil Nadu | B90: 483864.28 | D90: =A90 -> Tamil Nadu | E90: =GETPIVOTDATA("Amount_INR",$A$89,"State",D90) -> 483864.28
A91: Delhi | B91: 482240.36 | D91: =A91 -> Delhi | E91: =GETPIVOTDATA("Amount_INR",$A$89,"State",D91) -> 482240.36
A92: Karnataka | B92: 449368.73 | D92: =A92 -> Karnataka | E92: =GETPIVOTDATA("Amount_INR",$A$89,"State",D92) -> 449368.73
A93: Gujarat | B93: 423096.54 | D93: =A93 -> Gujarat | E93: =GETPIVOTDATA("Amount_INR",$A$89,"State",D93) -> 423096.54
A94: Madhya Pradesh | B94: 421480.56 | D94: =A94 -> Madhya Pradesh | E94: =GETPIVOTDATA("Amount_INR",$A$89,"State",D94) -> 421480.56
A95: Telangana | B95: 417633.9 | D95: =A95 -> Telangana | E95: =GETPIVOTDATA("Amount_INR",$A$89,"State",D95) -> 417633.9
A96: Uttar Pradesh | B96: 415795.12 | D96: =A96 -> Uttar Pradesh | E96: =GETPIVOTDATA("Amount_INR",$A$89,"State",D96) -> 415795.12
A97: West Bengal | B97: 398338.79 | D97: =A97 -> West Bengal | E97: =GETPIVOTDATA("Amount_INR",$A$89,"State",D97) -> 398338.79
A98: Rajasthan | B98: 398274.26 | D98: =A98 -> Rajasthan | E98: =GETPIVOTDATA("Amount_INR",$A$89,"State",D98) -> 398274.26
A99: Maharashtra | B99: 335629.17 | D99: =A99 -> Maharashtra | E99: =GETPIVOTDATA("Amount_INR",$A$89,"State",D99) -> 335629.17
A103: Row Labels | B103: Sum of Amount_INR
A104: Punjab National Bank | B104: 4129.91 | D104: =A104 -> Punjab National Bank | E104: =GETPIVOTDATA("Amount_INR",$A$103,"Bank_Name",D104)/100000 -> 0.0412991
A105: Bank of Baroda | B105: 484025.18 | D105: =A105 -> Bank of Baroda | E105: =GETPIVOTDATA("Amount_INR",$A$103,"Bank_Name",D105)/100000 -> 4.8402518
A106: Canara Bank | B106: 499190.94 | D106: =A106 -> Canara Bank | E106: =GETPIVOTDATA("Amount_INR",$A$103,"Bank_Name",D106)/100000 -> 4.9919094
A107: Kotak Mahindra Bank | B107: 506511.35 | D107: =A107 -> Kotak Mahindra Bank | E107: =GETPIVOTDATA("Amount_INR",$A$103,"Bank_Name",D107)/100000 -> 5.0651135
A108: Axis Bank | B108: 545032.3 | D108: =A108 -> Axis Bank | E108: =GETPIVOTDATA("Amount_INR",$A$103,"Bank_Name",D108)/100000 -> 5.450323
A109: ICICI Bank | B109: 554183.69 | D109: =A109 -> ICICI Bank | E109: =GETPIVOTDATA("Amount_INR",$A$103,"Bank_Name",D109)/100000 -> 5.5418369
A110: SBI | B110: 720938.53 | D110: =A110 -> SBI | E110: =GETPIVOTDATA("Amount_INR",$A$103,"Bank_Name",D110)/100000 -> 7.2093853
A111: HDFC Bank | B111: 911709.81
A112: Row Labels | B112: Sum of Amount_INR
A113: Wallet Transfer | B113: 120435.25 | D113: =A113 -> Wallet Transfer | E113: =GETPIVOTDATA("Amount_INR",$A$112,"Transaction_Type",D113)/1000000 -> 0.12043525
A114: Subscription | B114: 225107.37 | D114: =A114 -> Subscription | E114: =GETPIVOTDATA("Amount_INR",$A$112,"Transaction_Type",D114)/1000000 -> 0.22510737
A115: Recharge | B115: 350782.69 | D115: =A115 -> Recharge | E115: =GETPIVOTDATA("Amount_INR",$A$112,"Transaction_Type",D115)/1000000 -> 0.35078269
A116: Online Shopping | B116: 414949.16 | D116: =A116 -> Online Shopping | E116: =GETPIVOTDATA("Amount_INR",$A$112,"Transaction_Type",D116)/1000000 -> 0.41494916
A117: Bill Payment | B117: 610393.17 | D117: =A117 -> Bill Payment | E117: =GETPIVOTDATA("Amount_INR",$A$112,"Transaction_Type",D117)/1000000 -> 0.61039317
A118: P2P | B118: 845933.01 | D118: =A118 -> P2P | E118: =GETPIVOTDATA("Amount_INR",$A$112,"Transaction_Type",D118)/1000000 -> 0.84593301
A119: P2M | B119: 1658121.1 | D119: =A119 -> P2M | E119: =GETPIVOTDATA("Amount_INR",$A$112,"Transaction_Type",D119)/1000000 -> 1.6581211
A123: Row Labels | B123: Sum of Amount_INR
A124: 0 | B124: 4606.66
A125: 1 | B125: 5506.15
A126: 2 | B126: 3684.14
A127: 3 | B127: 905.24
A128: 4 | B128: 1885.34
A129: 5 | B129: 6497.82
A130: 6 | B130: 21636.63
A131: 7 | B131: 49101.93
A132: 8 | B132: 147500.95
A133: 9 | B133: 274615.64
A134: 10 | B134: 278365.76
A135: 11 | B135: 238722.14
... A142: 18 | B142: 450168.68
A143: 19 | B143: 424833.99 | E143: hour | F143: amount
A144: 20 | B144: 351324.55 | E144: =A124 -> 0 | F144: =GETPIVOTDATA("Amount_INR",$A$123,"hour ",E144)/100000 -> 0.0460666
A145: 21 | B145: 180845.27 | E145: =A125 -> 1 | F145: =GETPIVOTDATA("Amount_INR",$A$123,"hour ",E145)/100000 -> 0.0550615
A146: 22 | B146: 86754.75 | E146: =A126 -> 2 | F146: =GETPIVOTDATA("Amount_INR",$A$123,"hour ",E146)/100000 -> 0.0368414
A147: 23 | B147: 19090.43 | E147: =A127 -> 3 | F147: =GETPIVOTDATA("Amount_INR",$A$123,"hour ",E147)/100000 -> 0.0090524
E148: =A128 -> 4 | F148: =GETPIVOTDATA("Amount_INR",$A$123,"hour ",E148)/100000 -> 0.0188534
E149: =A129 -> 5 | F149: =GETPIVOTDATA("Amount_INR",$A$123,"hour ",E149)/100000 -> 0.0649782
E150: =A130 -> 6 | F150: =GETPIVOTDATA("Amount_INR",$A$123,"hour ",E150)/100000 -> 0.2163663
E151: =A131 -> 7 | F151: =GETPIVOTDATA("Amount_INR",$A$123,"hour ",E151)/100000 -> 0.4910193
...

Sheet Sheet3
A2: ='pivot table'!A73 -> PhonePe | B2: =GETPIVOTDATA("Amount_INR",'pivot table'!$A$72,"UPI_App",A2) -> 0.474822
A3: ='pivot table'!A74 -> Google Pay | B3: =GETPIVOTDATA("Amount_INR",'pivot table'!$A$72,"UPI_App",A3) -> 0.21792867
A4: ='pivot table'!A75 -> Paytm | B4: =GETPIVOTDATA("Amount_INR",'pivot table'!$A$72,"UPI_App",A4) -> 0.15075786
A5: ='pivot table'!A76 -> Amazon Pay | B5: =GETPIVOTDATA("Amount_INR",'pivot table'!$A$72,"UPI_App",A5) -> 0.061717865
A6: ='pivot table'!A77 -> BHIM | B6: =GETPIVOTDATA("Amount_INR",'pivot table'!$A$72,"UPI_App",A6) -> 0.037513353
A7: ='pivot table'!A78 -> Cred Pay | B7: =GETPIVOTDATA("Amount_INR",'pivot table'!$A$72,"UPI_App",A7) -> 0.031827198
A8: ='pivot table'!A79 -> WhatsApp Pay | B8: =GETPIVOTDATA("Amount_INR",'pivot table'!$A$72,"UPI_App",A8) -> 0.025433057
A11: ='pivot table'!A83 -> Success | B11: =GETPIVOTDATA("Amount_INR",'pivot table'!$A$82,"Status",Sheet3!A11) -> 0.90920187
A12: ='pivot table'!A84 -> Failed | B12: =GETPIVOTDATA("Amount_INR",'pivot table'!$A$82,"Status",Sheet3!A12) -> 0.070434371
A13: ='pivot table'!A85 -> Pending | B13: =GETPIVOTDATA("Amount_INR",'pivot table'!$A$82,"Status",Sheet3!A13) -> 0.020363764
E20: Sum of Amount_INR | F20: Column Labels
E21: Row Labels | F21: 0 | G21: 1 | H21: 2 | I21: 3 | J21: 4 | K21: 5 | L21: 6 | M21: 7 | N21: 8 | O21: 9 | P21: 10 | Q21: 11 | R21: 12 | S21: 13 | T21: 14 | U21: 15 | V21: 16 | W21: 17 | X21: 18 | Y21: 19 | Z21: 20 | AA21: 21 | AB21: 22 | AC21: 23
E22: Sunday | G22: 91.58 | J22: 81.28 | L22: 1885.88 | M22: 7049.53 | N22: 32800.42 | O22: 25421.71 | P22: 77531.44 | Q22: 38182.39 | R22: 68664.53 | S22: 56108.2 | T22: 55596.22 | U22: 78874.23 | V22: 29382.65 | W22: 52104.01 | X22: 94137.6 | Y22: 76505.09 | Z22: 65625.29 | AA22: 22305.91 | AB22: 20787.42 | AC22: 1123.21
E23: Monday | F23: 276.4 | G23: 3311.85 | J23: 234.52 | L23: 1185.69 | M23: 7459.07 | N23: 20340.69 | O23: 22865.25 | P23: 38380.48 | Q23: 27690.51 | R23: 42243.29 | S23: 33792.29 | T23: 39410.07 | U23: 51425.68 | V23: 31706.57 | W23: 28817.93 | X23: 44663.32 | Y23: 45136.69 | Z23: 40648.83 | AA23: 30604.94 | AB23: 6964.64 | AC23: 659.27
E24: Tuesday | F24: 986.81 | H24: 1810.01 | J24: 402.45 | K24: 392.58 | L24: 773.35 | M24: 3009.05 | N24: 26589.82 | O24: 41959.89 | P24: 32912.14 | Q24: 21366.28 | R24: 38694.03 | S24: 20107.35 | T24: 30651.5 | U24: 46206 | V24: 27336.58 | W24: 29189.58 | X24: 68458.56 | Y24: 60389.46 | Z24: 32121.48 | AA24: 17822.97 | AB24: 4827.47 | AC24: 2708.07
E25: Wednesday | F25: 1643.85 | H25: 780.75 | I25: 368.58 | J25: 1167.09 | K25: 2409.86 | L25: 1063.73 | M25: 5203.16 | N25: 9393.34 | O25: 45865.54 | P25: 21343.51 | Q25: 40467.78 | R25: 33681.43 | S25: 39005.04 | T25: 22143.57 | U25: 27692.71 | V25: 28671.61 | W25: 34630.26 | X25: 50112.48 | Y25: 54524.65 | Z25: 31833.04 | AA25: 23635.3 | AB25: 9805.51 | AC25: 4149.56
E26: Thursday | F26: 1489.87 | G26: 472.88 | I26: 403.46 | K26: 3310.4 | L26: 5605.63 | M26: 5469.75 | N26: 27487.99 | O26: 39369.06 | P26: 38272.39 | Q26: 30630.13 | R26: 38294.57 | S26: 36331.18 | T26: 30024.43 | U26: 16200.16 | V26: 23779.29 | W26: 55787.34 | X26: 56655.98 | Y26: 66821.51 | Z26: 29341.33 | AA26: 14221.31 | AB26: 11269.96 | AC26: 4376.31
E27: Friday | G27: 404.82 | K27: 384.98 | L27: 7649.65 | M27: 11631.48 | N27: 11134.48 | O27: 44261.05 | P27: 30785.4 | Q27: 32501.79 | R27: 52485.2 | S27: 60014.2 | T27: 30546.46 | U27: 59207.89 | V27: 37282.33 | W27: 47746.14 | X27: 60099.7 | Y27: 66813.54 | Z27: 77422.14 | AA27: 41838.66 | AB27: 15407 | AC27: 3132.31
E28: Saturday | F28: 209.73 | G28: 1225.02 | H28: 1093.38 | I28: 133.2 | L28: 3472.7 | M28: 9279.89 | N28: 19754.21 | O28: 54873.14 | P28: 39140.4 | Q28: 47883.26 | R28: 45056.67 | S28: 49031.98 | T28: 35456.62 | U28: 40951.45 | V28: 29461.6 | W28: 45882.8 | X28: 76041.04 | Y28: 54643.05 | Z28: 74332.44 | AA28: 30416.18 | AB28: 17692.75 | AC28: 2941.7
B33: ='pivot table'!D90 -> Tamil Nadu | C33: =GETPIVOTDATA("Amount_INR",'pivot table'!$A$89,"State",B33)/100000 -> 4.8386428
B34: ='pivot table'!D91 -> Delhi | C34: =GETPIVOTDATA("Amount_INR",'pivot table'!$A$89,"State",B34)/100000 -> 4.8224036
B35: ='pivot table'!D92 -> Karnataka | C35: =GETPIVOTDATA("Amount_INR",'pivot table'!$A$89,"State",B35)/100000 -> 4.4936873
B36: ='pivot table'!D93 -> Gujarat | C36: =GETPIVOTDATA("Amount_INR",'pivot table'!$A$89,"State",B36)/100000 -> 4.2309654
B37: ='pivot table'!D94 -> Madhya Pradesh | C37: =GETPIVOTDATA("Amount_INR",'pivot table'!$A$89,"State",B37)/100000 -> 4.2148056
B38: ='pivot table'!D95 -> Telangana | C38: =GETPIVOTDATA("Amount_INR",'pivot table'!$A$89,"State",B38)/100000 -> 4.176339
B39: ='pivot table'!D96 -> Uttar Pradesh | C39: =GETPIVOTDATA("Amount_INR",'pivot table'!$A$89,"State",B39)/100000 -> 4.1579512
B40: ='pivot table'!D97 -> West Bengal | C40: =GETPIVOTDATA("Amount_INR",'pivot table'!$A$89,"State",B40)/100000 -> 3.9833879
B41: ='pivot table'!D98 -> Rajasthan | C41: =GETPIVOTDATA("Amount_INR",'pivot table'!$A$89,"State",B41)/100000 -> 3.9827426
B42: ='pivot table'!D99 -> Maharashtra | C42: =GETPIVOTDATA("Amount_INR",'pivot table'!$A$89,"State",B42)/100000 -> 3.3562917
F46: Sum of Amount_INR | G46: Column Labels
F47: Row Labels | G47: 0 | H47: 1 | I47: 2 | J47: 3 | K47: 4 | L47: 5 | M47: 6 | N47: 7 | O47: 8 | P47: 9 | Q47: 10 | R47: 11 | S47: 12 | T47: 13 | U47: 14 | V47: 15 | W47: 16 | X47: 17 | Y47: 18 | Z47: 19 | AA47: 20 | AB47: 21 | AC47: 22 | AD47: 23
F48: Sunday | H48: 91.58 | K48: 81.28 | M48: 1885.88 | N48: 7049.53 | O48: 32800.42 | P48: 25421.71 | Q48: 77531.44 | R48: 38182.39 | S48: 68664.53 | T48: 56108.2 | U48: 55596.22 | V48: 78874.23 | W48: 29382.65 | X48: 52104.01 | Y48: 94137.6 | Z48: 76505.09 | AA48: 65625.29 | AB48: 22305.91 | AC48: 20787.42 | AD48: 1123.21
F49: Monday | G49: 276.4 | H49: 3311.85 | K49: 234.52 | M49: 1185.69 | N49: 7459.07 | O49: 20340.69 | P49: 22865.25 | Q49: 38380.48 | R49: 27690.51 | S49: 42243.29 | T49: 33792.29 | U49: 39410.07 | V49: 51425.68 | W49: 31706.57 | X49: 28817.93 | Y49: 44663.32 | Z49: 45136.69 | AA49: 40648.83 | AB49: 30604.94 | AC49: 6964.64 | AD49: 659.27
F50: Tuesday | G50: 986.81 | I50: 1810.01 | K50: 402.45 | L50: 392.58 | M50: 773.35 | N50: 3009.05 | O50: 26589.82 | P50: 41959.89 | Q50: 32912.14 | R50: 21366.28 | S50: 38694.03 | T50: 20107.35 | U50: 30651.5 | V50: 46206 | W50: 27336.58 | X50: 29189.58 | Y50: 68458.56 | Z50: 60389.46 | AA50: 32121.48 | AB50: 17822.97 | AC50: 4827.47 | AD50: 2708.07
F51: Wednesday | G51: 1643.85 | I51: 780.75 | J51: 368.58 | K51: 1167.09 | L51: 2409.86 | M51: 1063.73 | N51: 5203.16 | O51: 9393.34 | P51: 45865.54 | Q51: 21343.51 | R51: 40467.78 | S51: 33681.43 | T51: 39005.04 | U51: 22143.57 | V51: 27692.71 | W51: 28671.61 | X51: 34630.26 | Y51: 50112.48 | Z51: 54524.65 | AA51: 31833.04 | AB51: 23635.3 | AC51: 9805.51 | AD51: 4149.56
F52: Thursday | G52: 1489.87 | H52: 472.88 | J52: 403.46 | L52: 3310.4 | M52: 5605.63 | N52: 5469.75 | O52: 27487.99 | P52: 39369.06 | Q52: 38272.39 | R52: 30630.13 | S52: 38294.57 | T52: 36331.18 | U52: 30024.43 | V52: 16200.16 | W52: 23779.29 | X52: 55787.34 | Y52: 56655.98 | Z52: 66821.51 | AA52: 29341.33 | AB52: 14221.31 | AC52: 11269.96 | AD52: 4376.31
F53: Friday | H53: 404.82 | L53: 384.98 | M53: 7649.65 | N53: 11631.48 | O53: 11134.48 | P53: 44261.05 | Q53: 30785.4 | R53: 32501.79 | S53: 52485.2 | T53: 60014.2 | U53: 30546.46 | V53: 59207.89 | W53: 37282.33 | X53: 47746.14 | Y53: 60099.7 | Z53: 66813.54 | AA53: 77422.14 | AB53: 41838.66 | AC53: 15407 | AD53: 3132.31
F54: Saturday | G54: 209.73 | H54: 1225.02 | I54: 1093.38 | J54: 133.2 | M54: 3472.7 | N54: 9279.89 | O54: 19754.21 | P54: 54873.14 | Q54: 39140.4 | R54: 47883.26 | S54: 45056.67 | T54: 49031.98 | U54: 35456.62 | V54: 40951.45 | W54: 29461.6 | X54: 45882.8 | Y54: 76041.04 | Z54: 54643.05 | AA54: 74332.44 | AB54: 30416.18 | AC54: 17692.75 | AD54: 2941.7
I62: day/hr | J62: =G47 -> 0 | K62: =H47 -> 1 | L62: =I47 -> 2 | M62: =J47 -> 3 | N62: =K47 -> 4 | O62: =L47 -> 5 | P62: =M47 -> 6 | Q62: =N47 -> 7 | ... AD62: =AA47 -> 20 | AF62: =AC47 -> 22
I63: =F48 -> Sunday | J63: =GETPIVOTDATA("Amount_INR",$F$46,"Day",I63,"hour ",$J$62)/10000 -> 0 | K63: =GETPIVOTDATA("Amount_INR",$F$46,"Day",I63,"hour ",$K$62)/10000 -> 0.009158 | L63: =GETPIVOTDATA("Amount_INR",$F$46,"Day",I63,"hour ",$L$62)/10000 -> 0 | M63: =GETPIVOTDATA("Amount_INR",$F$46,"Day",I63,"hour ",$M$62)/10000 -> 0 | N63: =GETPIVOTDATA("Amount_INR",$F$46,"Day",I63,"hour ",$N$62)/10000 -> 0.008128 | O63: =GETPIVOTDATA("Amount_INR",$F$46,"Day",I63,"hour ",$O$62)/10000 -> 0 | P63: =GETPIVOTDATA("Amount_INR",$F$46,"Day",I63,"hour ",$P$62)/10000 -> 0.188588 | Q63: =GETPIVOTDATA("Amount_INR",$F$46,"Day",I63,"hour ",$Q$62)/10000 -> 0.704953 | R63: =GETPIVOTDATA("Amount_INR",$F$46,"Day",I63,"hour ",$R$62)/10000 -> 3.280042 | S63: =GETPIVOTDATA("Amount_INR",$F$46,"Day",I63,"hour ",$S$62)/10000 -> 2.542171 | T63: =GETPIVOTDATA("Amount_INR",$F$46,"Day",I63,"hour ",$T$62)/10000 -> 7.753144 | U63: =GETPIVOTDATA("Amount_INR",$F$46,"Day",I63,"hour ",$U$62)/10000 -> 3.818239 | V63: =GETPIVOTDATA("Amount_INR",$F$46,"Day",I63,"hour ",$V$62)/10000 -> 6.866453 | W63: =GETPIVOTDATA("Amount_INR",$F$46,"Day",I63,"hour ",$W$62)/10000 -> 5.61082 | X63: =GETPIVOTDATA("Amount_INR",$F$46,"Day",I63,"hour ",$X$62)/10000 -> 5.559622 | Y63: =GETPIVOTDATA("Amount_INR",$F$46,"Day",I63,"hour ",$Y$62)/10000 -> 7.887423 | Z63: =GETPIVOTDATA("Amount_INR",$F$46,"Day",I63,"hour ",$Z$62)/10000 -> 2.938265 | AA63: =GETPIVOTDATA("Amount_INR",$F$46,"Day",I63,"hour ",$AA$62)/10000 -> 5.210401 | AB63: =GETPIVOTDATA("Amount_INR",$F$46,"Day",I63,"hour ",$AB$62)/10000 -> 9.41376 | AC63: =GETPIVOTDATA("Amount_INR",$F$46,"Day",I63,"hour ",$AC$62)/10000 -> 7.650509 | AD63: =GETPIVOTDATA("Amount_INR",$F$46,"Day",I63,"hour ",$AD$62)/10000 -> 6.562529 | AE63: =GETPIVOTDATA("Amount_INR",$F$46,"Day",I63,"hour ",$AE$62)/10000 -> 0 | AF63: =GETPIVOTDATA("Amount_INR",$F$46,"Day",I63,"hour ",$AF$62)/10000 -> 2.078742 | AG63: =GETPIVOTDATA("Amount_INR",$F$46,"Day",I63,"hour ",$AG$62)/10000 -> 0
I64: =F49 -> Monday | J64: =GETPIVOTDATA("Amount_INR",$F$46,"Day",I64,"hour ",$J$62)/10000 -> 0.02764 | K64: =GETPIVOTDATA("Amount_INR",$F$46,"Day",I64,"hour ",$K$62)/10000 -> 0.331185 | L64: =GETPIVOTDATA("Amount_INR",$F$46,"Day",I64,"hour ",$L$62)/10000 -> 0 | M64: =GETPIVOTDATA("Amount_INR",$F$46,"Day",I64,"hour ",$M$62)/10000 -> 0 | N64: =GETPIVOTDATA("Amount_INR",$F$46,"Day",I64,"hour ",$N$62)/10000 -> 0.023452 | O64: =GETPIVOTDATA("Amount_INR",$F$46,"Day",I64,"hour ",$O$62)/10000 -> 0 | P64: =GETPIVOTDATA("Amount_INR",$F$46,"Day",I64,"hour ",$P$62)/10000 -> 0.118569 | Q64: =GETPIVOTDATA("Amount_INR",$F$46,"Day",I64,"hour ",$Q$62)/10000 -> 0.745907 | R64: =GETPIVOTDATA("Amount_INR",$F$46,"Day",I64,"hour ",$R$62)/10000 -> 2.034069 | S64: =GETPIVOTDATA("Amount_INR",$F$46,"Day",I64,"hour ",$S$62)/10000 -> 2.286525 | T64: =GETPIVOTDATA("Amount_INR",$F$46,"Day",I64,"hour ",$T$62)/10000 -> 3.838048 | U64: =GETPIVOTDATA("Amount_INR",$F$46,"Day",I64,"hour ",$U$62)/10000 -> 2.769051 | V64: =GETPIVOTDATA("Amount_INR",$F$46,"Day",I64,"hour ",$V$62)/10000 -> 4.224329 | W64: =GETPIVOTDATA("Amount_INR",$F$46,"Day",I64,"hour ",$W$62)/10000 -> 3.379229 | X64: =GETPIVOTDATA("Amount_INR",$F$46,"Day",I64,"hour ",$X$62)/10000 -> 3.941007 | Y64: =GETPIVOTDATA("Amount_INR",$F$46,"Day",I64,"hour ",$Y$62)/10000 -> 5.142568 | Z64: =GETPIVOTDATA("Amount_INR",$F$46,"Day",I64,"hour ",$Z$62)/10000 -> 3.170657 | AA64: =GETPIVOTDATA("Amount_INR",$F$46,"Day",I64,"hour ",$AA$62)/10000 -> 2.881793 | AB64: =GETPIVOTDATA("Amount_INR",$F$46,"Day",I64,"hour ",$AB$62)/10000 -> 4.466332 | AC64: =GETPIVOTDATA("Amount_INR",$F$46,"Day",I64,"hour ",$AC$62)/10000 -> 4.513669 | AD64: =GETPIVOTDATA("Amount_INR",$F$46,"Day",I64,"hour ",$AD$62)/10000 -> 4.064883 | AE64: =GETPIVOTDATA("Amount_INR",$F$46,"Day",I64,"hour ",$AE$62)/10000 -> 0.02764 | AF64: =GETPIVOTDATA("Amount_INR",$F$46,"Day",I64,"hour ",$AF$62)/10000 -> 0.696464 | AG64: =GETPIVOTDATA("Amount_INR",$F$46,"Day",I64,"hour ",$AG$62)/10000 -> 0.02764
I65: =F50 -> Tuesday | J65: =GETPIVOTDATA("Amount_INR",$F$46,"Day",I65,"hour ",$J$62)/10000 -> 0.098681 | K65: =GETPIVOTDATA("Amount_INR",$F$46,"Day",I65,"hour ",$K$62)/10000 -> 0 | L65: =GETPIVOTDATA("Amount_INR",$F$46,"Day",I65,"hour ",$L$62)/10000 -> 0.181001 | M65: =GETPIVOTDATA("Amount_INR",$F$46,"Day",I65,"hour ",$M$62)/10000 -> 0 | N65: =GETPIVOTDATA("Amount_INR",$F$46,"Day",I65,"hour ",$N$62)/10000 -> 0.040245 | O65: =GETPIVOTDATA("Amount_INR",$F$46,"Day",I65,"hour ",$O$62)/10000 -> 0.039258 | P65: =GETPIVOTDATA("Amount_INR",$F$46,"Day",I65,"hour ",$P$62)/10000 -> 0.077335 | Q65: =GETPIVOTDATA("Amount_INR",$F$46,"Day",I65,"hour ",$Q$62)/10000 -> 0.300905 | R65: =GETPIVOTDATA("Amount_INR",$F$46,"Day",I65,"hour ",$R$62)/10000 -> 2.658982 | S65: =GETPIVOTDATA("Amount_INR",$F$46,"Day",I65,"hour ",$S$62)/10000 -> 4.195989 | T65: =GETPIVOTDATA("Amount_INR",$F$46,"Day",I65,"hour ",$T$62)/10000 -> 3.291214 | U65: =GETPIVOTDATA("Amount_INR",$F$46,"Day",I65,"hour ",$U$62)/10000 -> 2.136628 | V65: =GETPIVOTDATA("Amount_INR",$F$46,"Day",I65,"hour ",$V$62)/10000 -> 3.869403 | W65: =GETPIVOTDATA("Amount_INR",$F$46,"Day",I65,"hour ",$W$62)/10000 -> 2.010735 | X65: =GETPIVOTDATA("Amount_INR",$F$46,"Day",I65,"hour ",$X$62)/10000 -> 3.06515 | Y65: =GETPIVOTDATA("Amount_INR",$F$46,"Day",I65,"hour ",$Y$62)/10000 -> 4.6206 | Z65: =GETPIVOTDATA("Amount_INR",$F$46,"Day",I65,"hour ",$Z$62)/10000 -> 2.733658 | AA65: =GETPIVOTDATA("Amount_INR",$F$46,"Day",I65,"hour ",$AA$62)/10000 -> 2.918958 | AB65: =GETPIVOTDATA("Amount_INR",$F$46,"Day",I65,"hour ",$AB$62)/10000 -> 6.845856 | AC65: =GETPIVOTDATA("Amount_INR",$F$46,"Day",I65,"hour ",$AC$62)/10000 -> 6.038946 | AD65: =GETPIVOTDATA("Amount_INR",$F$46,"Day",I65,"hour ",$AD$62)/10000 -> 3.212148 | AE65: =GETPIVOTDATA("Amount_INR",$F$46,"Day",I65,"hour ",$AE$62)/10000 -> 0.098681 | AF65: =GETPIVOTDATA("Amount_INR",$F$46,"Day",I65,"hour ",$AF$62)/10000 -> 0.482747 | AG65: =GETPIVOTDATA("Amount_INR",$F$46,"Day",I65,"hour ",$AG$62)/10000 -> 0.098681
I66: =F51 -> Wednesday | J66: =GETPIVOTDATA("Amount_INR",$F$46,"Day",I66,"hour ",$J$62)/10000 -> 0.164385 | K66: =GETPIVOTDATA("Amount_INR",$F$46,"Day",I66,"hour ",$K$62)/10000 -> 0 | L66: =GETPIVOTDATA("Amount_INR",$F$46,"Day",I66,"hour ",$L$62)/10000 -> 0.078075 | M66: =GETPIVOTDATA("Amount_INR",$F$46,"Day",I66,"hour ",$M$62)/10000 -> 0.036858 | N66: =GETPIVOTDATA("Amount_INR",$F$46,"Day",I66,"hour ",$N$62)/10000 -> 0.116709 | O66: =GETPIVOTDATA("Amount_INR",$F$46,"Day",I66,"hour ",$O$62)/10000 -> 0.240986 | P66: =GETPIVOTDATA("Amount_INR",$F$46,"Day",I66,"hour ",$P$62)/10000 -> 0.106373 | Q66: =GETPIVOTDATA("Amount_INR",$F$46,"Day",I66,"hour ",$Q$62)/10000 -> 0.520316 | R66: =GETPIVOTDATA("Amount_INR",$F$46,"Day",I66,"hour ",$R$62)/10000 -> 0.939334 | S66: =GETPIVOTDATA("Amount_INR",$F$46,"Day",I66,"hour ",$S$62)/10000 -> 4.586554 | T66: =GETPIVOTDATA("Amount_INR",$F$46,"Day",I66,"hour ",$T$62)/10000 -> 2.134351 | U66: =GETPIVOTDATA("Amount_INR",$F$46,"Day",I66,"hour ",$U$62)/10000 -> 4.046778 | V66: =GETPIVOTDATA("Amount_INR",$F$46,"Day",I66,"hour ",$V$62)/10000 -> 3.368143 | W66: =GETPIVOTDATA("Amount_INR",$F$46,"Day",I66,"hour ",$W$62)/10000 -> 3.900504 | X66: =GETPIVOTDATA("Amount_INR",$F$46,"Day",I66,"hour ",$X$62)/10000 -> 2.214357 | Y66: =GETPIVOTDATA("Amount_INR",$F$46,"Day",I66,"hour ",$Y$62)/10000 -> 2.769271 | Z66: =GETPIVOTDATA("Amount_INR",$F$46,"Day",I66,"hour ",$Z$62)/10000 -> 2.867161 | AA66: =GETPIVOTDATA("Amount_INR",$F$46,"Day",I66,"hour ",$AA$62)/10000 -> 3.463026 | AB66: =GETPIVOTDATA("Amount_INR",$F$46,"Day",I66,"hour ",$AB$62)/10000 -> 5.011248 | AC66: =GETPIVOTDATA("Amount_INR",$F$46,"Day",I66,"hour ",$AC$62)/10000 -> 5.452465 | AD66: =GETPIVOTDATA("Amount_INR",$F$46,"Day",I66,"hour ",$AD$62)/10000 -> 3.183304 | AE66: =GETPIVOTDATA("Amount_INR",$F$46,"Day",I66,"hour ",$AE$62)/10000 -> 0.164385 | AF66: =GETPIVOTDATA("Amount_INR",$F$46,"Day",I66,"hour ",$AF$62)/10000 -> 0.980551 | AG66: =GETPIVOTDATA("Amount_INR",$F$46,"Day",I66,"hour ",$AG$62)/10000 -> 0.164385
I67: =F52 -> Thursday | J67: =GETPIVOTDATA("Amount_INR",$F$46,"Day",I67,"hour ",$J$62)/10000 -> 0.148987 | K67: =GETPIVOTDATA("Amount_INR",$F$46,"Day",I67,"hour ",$K$62)/10000 -> 0.047288 | L67: =GETPIVOTDATA("Amount_INR",$F$46,"Day",I67,"hour ",$L$62)/10000 -> 0 | M67: =GETPIVOTDATA("Amount_INR",$F$46,"Day",I67,"hour ",$M$62)/10000 -> 0.040346 | N67: =GETPIVOTDATA("Amount_INR",$F$46,"Day",I67,"hour ",$N$62)/10000 -> 0 | O67: =GETPIVOTDATA("Amount_INR",$F$46,"Day",I67,"hour ",$O$62)/10000 -> 0.33104 | P67: =GETPIVOTDATA("Amount_INR",$F$46,"Day",I67,"hour ",$P$62)/10000 -> 0.560563 | Q67: =GETPIVOTDATA("Amount_INR",$F$46,"Day",I67,"hour ",$Q$62)/10000 -> 0.546975 | R67: =GETPIVOTDATA("Amount_INR",$F$46,"Day",I67,"hour ",$R$62)/10000 -> 2.748799 | S67: =GETPIVOTDATA("Amount_INR",$F$46,"Day",I67,"hour ",$S$62)/10000 -> 3.936906 | T67: =GETPIVOTDATA("Amount_INR",$F$46,"Day",I67,"hour ",$T$62)/10000 -> 3.827239 | U67: =GETPIVOTDATA("Amount_INR",$F$46,"Day",I67,"hour ",$U$62)/10000 -> 3.063013 | V67: =GETPIVOTDATA("Amount_INR",$F$46,"Day",I67,"hour ",$V$62)/10000 -> 3.829457 | W67: =GETPIVOTDATA("Amount_INR",$F$46,"Day",I67,"hour ",$W$62)/10000 -> 3.633118 | X67: =GETPIVOTDATA("Amount_INR",$F$46,"Day",I67,"hour ",$X$62)/10000 -> 3.002443 | Y67: =GETPIVOTDATA("Amount_INR",$F$46,"Day",I67,"hour ",$Y$62)/10000 -> 1.620016 | Z67: =GETPIVOTDATA("Amount_INR",$F$46,"Day",I67,"hour ",$Z$62)/10000 -> 2.377929 | AA67: =GETPIVOTDATA("Amount_INR",$F$46,"Day",I67,"hour ",$AA$62)/10000 -> 5.578734 | AB67: =GETPIVOTDATA("Amount_INR",$F$46,"Day",I67,"hour ",$AB$62)/10000 -> 5.665598 | AC67: =GETPIVOTDATA("Amount_INR",$F$46,"Day",I67,"hour ",$AC$62)/10000 -> 6.682151 | AD67: =GETPIVOTDATA("Amount_INR",$F$46,"Day",I67,"hour ",$AD$62)/10000 -> 2.934133 | AE67: =GETPIVOTDATA("Amount_INR",$F$46,"Day",I67,"hour ",$AE$62)/10000 -> 0.148987 | AF67: =GETPIVOTDATA("Amount_INR",$F$46,"Day",I67,"hour ",$AF$62)/10000 -> 1.126996 | AG67: =GETPIVOTDATA("Amount_INR",$F$46,"Day",I67,"hour ",$AG$62)/10000 -> 0.148987
I68: =F53 -> Friday | J68: =GETPIVOTDATA("Amount_INR",$F$46,"Day",I68,"hour ",$J$62)/10000 -> 0 | K68: =GETPIVOTDATA("Amount_INR",$F$46,"Day",I68,"hour ",$K$62)/10000 -> 0.040482 | L68: =GETPIVOTDATA("Amount_INR",$F$46,"Day",I68,"hour ",$L$62)/10000 -> 0 | M68: =GETPIVOTDATA("Amount_INR",$F$46,"Day",I68,"hour ",$M$62)/10000 -> 0 | N68: =GETPIVOTDATA("Amount_INR",$F$46,"Day",I68,"hour ",$N$62)/10000 -> 0 | O68: =GETPIVOTDATA("Amount_INR",$F$46,"Day",I68,"hour ",$O$62)/10000 -> 0.038498 | P68: =GETPIVOTDATA("Amount_INR",$F$46,"Day",I68,"hour ",$P$62)/10000 -> 0.764965 | Q68: =GETPIVOTDATA("Amount_INR",$F$46,"Day",I68,"hour ",$Q$62)/10000 -> 1.163148 | R68: =GETPIVOTDATA("Amount_INR",$F$46,"Day",I68,"hour ",$R$62)/10000 -> 1.113448 | S68: =GETPIVOTDATA("Amount_INR",$F$46,"Day",I68,"hour ",$S$62)/10000 -> 4.426105 | T68: =GETPIVOTDATA("Amount_INR",$F$46,"Day",I68,"hour ",$T$62)/10000 -> 3.07854 | U68: =GETPIVOTDATA("Amount_INR",$F$46,"Day",I68,"hour ",$U$62)/10000 -> 3.250179 | V68: =GETPIVOTDATA("Amount_INR",$F$46,"Day",I68,"hour ",$V$62)/10000 -> 5.24852 | W68: =GETPIVOTDATA("Amount_INR",$F$46,"Day",I68,"hour ",$W$62)/10000 -> 6.00142 | X68: =GETPIVOTDATA("Amount_INR",$F$46,"Day",I68,"hour ",$X$62)/10000 -> 3.054646 | Y68: =GETPIVOTDATA("Amount_INR",$F$46,"Day",I68,"hour ",$Y$62)/10000 -> 5.920789 | Z68: =GETPIVOTDATA("Amount_INR",$F$46,"Day",I68,"hour ",$Z$62)/10000 -> 3.728233 | AA68: =GETPIVOTDATA("Amount_INR",$F$46,"Day",I68,"hour ",$AA$62)/10000 -> 4.774614 | AB68: =GETPIVOTDATA("Amount_INR",$F$46,"Day",I68,"hour ",$AB$62)/10000 -> 6.00997 | AC68: =GETPIVOTDATA("Amount_INR",$F$46,"Day",I68,"hour ",$AC$62)/10000 -> 6.681354 | AD68: =GETPIVOTDATA("Amount_INR",$F$46,"Day",I68,"hour ",$AD$62)/10000 -> 7.742214 | AE68: =GETPIVOTDATA("Amount_INR",$F$46,"Day",I68,"hour ",$AE$62)/10000 -> 0 | AF68: =GETPIVOTDATA("Amount_INR",$F$46,"Day",I68,"hour ",$AF$62)/10000 -> 1.5407 | AG68: =GETPIVOTDATA("Amount_INR",$F$46,"Day",I68,"hour ",$AG$62)/10000 -> 0
I69: =F54 -> Saturday | J69: =GETPIVOTDATA("Amount_INR",$F$46,"Day",I69,"hour ",$J$62)/10000 -> 0.020973 | K69: =GETPIVOTDATA("Amount_INR",$F$46,"Day",I69,"hour ",$K$62)/10000 -> 0.122502 | L69: =GETPIVOTDATA("Amount_INR",$F$46,"Day",I69,"hour ",$L$62)/10000 -> 0.109338 | M69: =GETPIVOTDATA("Amount_INR",$F$46,"Day",I69,"hour ",$M$62)/10000 -> 0.01332 | N69: =GETPIVOTDATA("Amount_INR",$F$46,"Day",I69,"hour ",$N$62)/10000 -> 0 | O69: =GETPIVOTDATA("Amount_INR",$F$46,"Day",I69,"hour ",$O$62)/10000 -> 0 | P69: =GETPIVOTDATA("Amount_INR",$F$46,"Day",I69,"hour ",$P$62)/10000 -> 0.34727 | Q69: =GETPIVOTDATA("Amount_INR",$F$46,"Day",I69,"hour ",$Q$62)/10000 -> 0.927989 | R69: =GETPIVOTDATA("Amount_INR",$F$46,"Day",I69,"hour ",$R$62)/10000 -> 1.975421 | S69: =GETPIVOTDATA("Amount_INR",$F$46,"Day",I69,"hour ",$S$62)/10000 -> 5.487314 | T69: =GETPIVOTDATA("Amount_INR",$F$46,"Day",I69,"hour ",$T$62)/10000 -> 3.91404 | U69: =GETPIVOTDATA("Amount_INR",$F$46,"Day",I69,"hour ",$U$62)/10000 -> 4.788326 | V69: =GETPIVOTDATA("Amount_INR",$F$46,"Day",I69,"hour ",$V$62)/10000 -> 4.505667 | W69: =GETPIVOTDATA("Amount_INR",$F$46,"Day",I69,"hour ",$W$62)/10000 -> 4.903198 | X69: =GETPIVOTDATA("Amount_INR",$F$46,"Day",I69,"hour ",$X$62)/10000 -> 3.545662 | Y69: =GETPIVOTDATA("Amount_INR",$F$46,"Day",I69,"hour ",$Y$62)/10000 -> 4.095145 | Z69: =GETPIVOTDATA("Amount_INR",$F$46,"Day",I69,"hour ",$Z$62)/10000 -> 2.94616 | AA69: =GETPIVOTDATA("Amount_INR",$F$46,"Day",I69,"hour ",$AA$62)/10000 -> 4.58828 | AB69: =GETPIVOTDATA("Amount_INR",$F$46,"Day",I69,"hour ",$AB$62)/10000 -> 7.604104 | AC69: =GETPIVOTDATA("Amount_INR",$F$46,"Day",I69,"hour ",$AC$62)/10000 -> 5.464305 | AD69: =GETPIVOTDATA("Amount_INR",$F$46,"Day",I69,"hour ",$AD$62)/10000 -> 7.433244 | AE69: =GETPIVOTDATA("Amount_INR",$F$46,"Day",I69,"hour ",$AE$62)/10000 -> 0.020973 | AF69: =GETPIVOTDATA("Amount_INR",$F$46,"Day",I69,"hour ",$AF$62)/10000 -> 1.769275 | AG69: =GETPIVOTDATA("Amount_INR",$F$46,"Day",I69,"hour ",$AG$62)/10000 -> 0.020973
